[
  {
    "t": "2024-02-16T15:15:00+05:30",
    "o": 1703.9,
    "h": 1704.75,
    "l": 1698.35,
    "c": 1698.65,
    "v": 506214
  },
  {
    "t": "2024-02-16T14:15:00+05:30",
    "o": 1702.2,
    "h": 1705,
    "l": 1697.45,
    "c": 1703.65,
    "v": 1387478
  },
  {
    "t": "2024-02-16T13:15:00+05:30",
    "o": 1699.15,
    "h": 1703,
    "l": 1695,
    "c": 1702.2,
    "v": 667063
  },
  {
    "t": "2024-02-16T12:15:00+05:30",
    "o": 1695.1,
    "h": 1702.1,
    "l": 1694.95,
    "c": 1699.15,
    "v": 657820
  },
  {
    "t": "2024-02-16T11:15:00+05:30",
    "o": 1698.4,
    "h": 1699.65,
    "l": 1694.75,
    "c": 1695.1,
    "v": 415356
  },
  {
    "t": "2024-02-16T10:15:00+05:30",
    "o": 1698.05,
    "h": 1701.15,
    "l": 1695.75,
    "c": 1698.4,
    "v": 378735
  },
  {
    "t": "2024-02-16T09:15:00+05:30",
    "o": 1689,
    "h": 1709,
    "l": 1687.95,
    "c": 1698,
    "v": 837193
  },
  {
    "t": "2024-02-15T15:15:00+05:30",
    "o": 1676.5,
    "h": 1680.35,
    "l": 1675.75,
    "c": 1680,
    "v": 489981
  },
  {
    "t": "2024-02-15T14:15:00+05:30",
    "o": 1674.25,
    "h": 1677.4,
    "l": 1670.95,
    "c": 1676.3,
    "v": 1161214
  },
  {
    "t": "2024-02-15T13:15:00+05:30",
    "o": 1667.8,
    "h": 1679,
    "l": 1667.25,
    "c": 1674.4,
    "v": 627593
  },
  {
    "t": "2024-02-15T12:15:00+05:30",
    "o": 1666.65,
    "h": 1669.45,
    "l": 1661.6,
    "c": 1668,
    "v": 513471
  },
  {
    "t": "2024-02-15T11:15:00+05:30",
    "o": 1671.2,
    "h": 1673.4,
    "l": 1665.45,
    "c": 1666.75,
    "v": 685149
  },
  {
    "t": "2024-02-15T10:15:00+05:30",
    "o": 1681.35,
    "h": 1682.7,
    "l": 1669.05,
    "c": 1671.2,
    "v": 558543
  },
  {
    "t": "2024-02-15T09:15:00+05:30",
    "o": 1677,
    "h": 1687.75,
    "l": 1670,
    "c": 1681,
    "v": 783536
  },
  {
    "t": "2024-02-14T15:15:00+05:30",
    "o": 1665.1,
    "h": 1669.45,
    "l": 1664,
    "c": 1667,
    "v": 222696
  },
  {
    "t": "2024-02-14T14:15:00+05:30",
    "o": 1654.3,
    "h": 1668,
    "l": 1652.8,
    "c": 1665.2,
    "v": 572706
  },
  {
    "t": "2024-02-14T13:15:00+05:30",
    "o": 1648,
    "h": 1655,
    "l": 1646.55,
    "c": 1654.35,
    "v": 347898
  },
  {
    "t": "2024-02-14T12:15:00+05:30",
    "o": 1640.25,
    "h": 1649.5,
    "l": 1640.1,
    "c": 1648,
    "v": 412005
  },
  {
    "t": "2024-02-14T11:15:00+05:30",
    "o": 1642.05,
    "h": 1644.25,
    "l": 1635.5,
    "c": 1640.05,
    "v": 728405
  },
  {
    "t": "2024-02-14T10:15:00+05:30",
    "o": 1644.2,
    "h": 1648.4,
    "l": 1639.55,
    "c": 1642.1,
    "v": 421575
  },
  {
    "t": "2024-02-14T09:15:00+05:30",
    "o": 1660.2,
    "h": 1665,
    "l": 1638.8,
    "c": 1644.6,
    "v": 1042933
  },
  {
    "t": "2024-02-13T15:15:00+05:30",
    "o": 1688.35,
    "h": 1688.55,
    "l": 1678.2,
    "c": 1680.35,
    "v": 231220
  },
  {
    "t": "2024-02-13T14:15:00+05:30",
    "o": 1674.8,
    "h": 1689,
    "l": 1673.65,
    "c": 1688.3,
    "v": 624317
  },
  {
    "t": "2024-02-13T13:15:00+05:30",
    "o": 1676.4,
    "h": 1677.95,
    "l": 1673.05,
    "c": 1674.8,
    "v": 334873
  },
  {
    "t": "2024-02-13T12:15:00+05:30",
    "o": 1668.55,
    "h": 1679.85,
    "l": 1667.6,
    "c": 1676.4,
    "v": 308564
  },
  {
    "t": "2024-02-13T11:15:00+05:30",
    "o": 1677.7,
    "h": 1678.9,
    "l": 1668.5,
    "c": 1668.5,
    "v": 247737
  },
  {
    "t": "2024-02-13T10:15:00+05:30",
    "o": 1674.45,
    "h": 1678.95,
    "l": 1669.55,
    "c": 1677.95,
    "v": 306448
  },
  {
    "t": "2024-02-13T09:15:00+05:30",
    "o": 1683,
    "h": 1689.1,
    "l": 1663.5,
    "c": 1674.45,
    "v": 632023
  },
  {
    "t": "2024-02-12T15:15:00+05:30",
    "o": 1679.9,
    "h": 1680.25,
    "l": 1676.75,
    "c": 1677.2,
    "v": 179041
  },
  {
    "t": "2024-02-12T14:15:00+05:30",
    "o": 1687,
    "h": 1687.8,
    "l": 1678.5,
    "c": 1679.8,
    "v": 549208
  },
  {
    "t": "2024-02-12T13:15:00+05:30",
    "o": 1690.4,
    "h": 1691,
    "l": 1684,
    "c": 1687.6,
    "v": 379037
  },
  {
    "t": "2024-02-12T12:15:00+05:30",
    "o": 1685.1,
    "h": 1691.55,
    "l": 1684.05,
    "c": 1690.3,
    "v": 506184
  },
  {
    "t": "2024-02-12T11:15:00+05:30",
    "o": 1681.4,
    "h": 1691,
    "l": 1680,
    "c": 1685.1,
    "v": 633276
  },
  {
    "t": "2024-02-12T10:15:00+05:30",
    "o": 1682.55,
    "h": 1685.4,
    "l": 1675.45,
    "c": 1681.4,
    "v": 702781
  },
  {
    "t": "2024-02-12T09:15:00+05:30",
    "o": 1670.35,
    "h": 1692.95,
    "l": 1670.35,
    "c": 1682.45,
    "v": 596632
  },
  {
    "t": "2024-02-09T15:15:00+05:30",
    "o": 1669.85,
    "h": 1671.35,
    "l": 1667.2,
    "c": 1670.7,
    "v": 269762
  },
  {
    "t": "2024-02-09T14:15:00+05:30",
    "o": 1675.25,
    "h": 1677.85,
    "l": 1663.15,
    "c": 1669.8,
    "v": 690282
  },
  {
    "t": "2024-02-09T13:15:00+05:30",
    "o": 1661.3,
    "h": 1676.5,
    "l": 1661.1,
    "c": 1675,
    "v": 544191
  },
  {
    "t": "2024-02-09T12:15:00+05:30",
    "o": 1661.25,
    "h": 1665.75,
    "l": 1659.8,
    "c": 1661.35,
    "v": 623114
  },
  {
    "t": "2024-02-09T11:15:00+05:30",
    "o": 1665.4,
    "h": 1667,
    "l": 1660,
    "c": 1661.45,
    "v": 685293
  },
  {
    "t": "2024-02-09T10:15:00+05:30",
    "o": 1668.65,
    "h": 1671.95,
    "l": 1660,
    "c": 1665.35,
    "v": 772611
  },
  {
    "t": "2024-02-09T09:15:00+05:30",
    "o": 1684.7,
    "h": 1692.9,
    "l": 1667.2,
    "c": 1669.2,
    "v": 994360
  },
  {
    "t": "2024-02-08T15:15:00+05:30",
    "o": 1692.6,
    "h": 1693.95,
    "l": 1690.85,
    "c": 1693,
    "v": 652165
  },
  {
    "t": "2024-02-08T14:15:00+05:30",
    "o": 1690.85,
    "h": 1694.05,
    "l": 1688.15,
    "c": 1692.25,
    "v": 1477991
  },
  {
    "t": "2024-02-08T13:15:00+05:30",
    "o": 1691.25,
    "h": 1693.3,
    "l": 1689.25,
    "c": 1690.8,
    "v": 506139
  },
  {
    "t": "2024-02-08T12:15:00+05:30",
    "o": 1690,
    "h": 1693.35,
    "l": 1688,
    "c": 1691.4,
    "v": 433786
  },
  {
    "t": "2024-02-08T11:15:00+05:30",
    "o": 1684.8,
    "h": 1691,
    "l": 1682.8,
    "c": 1689.9,
    "v": 625555
  },
  {
    "t": "2024-02-08T10:15:00+05:30",
    "o": 1694.45,
    "h": 1699,
    "l": 1683.7,
    "c": 1684.7,
    "v": 1201351
  },
  {
    "t": "2024-02-08T09:15:00+05:30",
    "o": 1698,
    "h": 1706.35,
    "l": 1692.95,
    "c": 1694.6,
    "v": 1004519
  },
  {
    "t": "2024-02-07T15:15:00+05:30",
    "o": 1693.15,
    "h": 1696.7,
    "l": 1691.25,
    "c": 1694,
    "v": 578701
  },
  {
    "t": "2024-02-07T14:15:00+05:30",
    "o": 1697.2,
    "h": 1698,
    "l": 1690,
    "c": 1693,
    "v": 880008
  },
  {
    "t": "2024-02-07T13:15:00+05:30",
    "o": 1692.2,
    "h": 1698.5,
    "l": 1686.85,
    "c": 1697.9,
    "v": 546635
  },
  {
    "t": "2024-02-07T12:15:00+05:30",
    "o": 1697.85,
    "h": 1701.75,
    "l": 1690,
    "c": 1692.25,
    "v": 517412
  },
  {
    "t": "2024-02-07T11:15:00+05:30",
    "o": 1700.6,
    "h": 1704,
    "l": 1694.8,
    "c": 1697.75,
    "v": 687704
  },
  {
    "t": "2024-02-07T10:15:00+05:30",
    "o": 1712.1,
    "h": 1712.55,
    "l": 1698,
    "c": 1700.75,
    "v": 618254
  },
  {
    "t": "2024-02-07T09:15:00+05:30",
    "o": 1729,
    "h": 1729,
    "l": 1707.65,
    "c": 1712.05,
    "v": 752381
  },
  {
    "t": "2024-02-06T15:15:00+05:30",
    "o": 1728.65,
    "h": 1733,
    "l": 1726.1,
    "c": 1728,
    "v": 676687
  },
  {
    "t": "2024-02-06T14:15:00+05:30",
    "o": 1728.85,
    "h": 1731,
    "l": 1726.15,
    "c": 1728.55,
    "v": 1238017
  },
  {
    "t": "2024-02-06T13:15:00+05:30",
    "o": 1725.45,
    "h": 1731,
    "l": 1723.05,
    "c": 1728.75,
    "v": 796717
  },
  {
    "t": "2024-02-06T12:15:00+05:30",
    "o": 1720.95,
    "h": 1727.45,
    "l": 1720,
    "c": 1725.15,
    "v": 945558
  },
  {
    "t": "2024-02-06T11:15:00+05:30",
    "o": 1714.6,
    "h": 1722,
    "l": 1713.2,
    "c": 1720.8,
    "v": 943167
  },
  {
    "t": "2024-02-06T10:15:00+05:30",
    "o": 1715.6,
    "h": 1716.45,
    "l": 1705.1,
    "c": 1714.6,
    "v": 725455
  },
  {
    "t": "2024-02-06T09:15:00+05:30",
    "o": 1686.75,
    "h": 1720.7,
    "l": 1673.95,
    "c": 1714.7,
    "v": 2325781
  },
  {
    "t": "2024-02-05T15:15:00+05:30",
    "o": 1684.9,
    "h": 1687.8,
    "l": 1682.95,
    "c": 1683.4,
    "v": 492989
  },
  {
    "t": "2024-02-05T14:15:00+05:30",
    "o": 1693.85,
    "h": 1696,
    "l": 1681.85,
    "c": 1684.85,
    "v": 1201243
  },
  {
    "t": "2024-02-05T13:15:00+05:30",
    "o": 1695.55,
    "h": 1696.95,
    "l": 1690.2,
    "c": 1693.65,
    "v": 339921
  },
  {
    "t": "2024-02-05T12:15:00+05:30",
    "o": 1698.65,
    "h": 1700,
    "l": 1691.45,
    "c": 1695.55,
    "v": 240926
  },
  {
    "t": "2024-02-05T11:15:00+05:30",
    "o": 1695,
    "h": 1700.5,
    "l": 1693,
    "c": 1698.65,
    "v": 294587
  },
  {
    "t": "2024-02-05T10:15:00+05:30",
    "o": 1692.5,
    "h": 1697.75,
    "l": 1687,
    "c": 1695,
    "v": 455558
  },
  {
    "t": "2024-02-05T09:15:00+05:30",
    "o": 1693.95,
    "h": 1700.75,
    "l": 1684.4,
    "c": 1692.45,
    "v": 562207
  },
  {
    "t": "2024-02-02T15:15:00+05:30",
    "o": 1693.8,
    "h": 1694.4,
    "l": 1691.45,
    "c": 1693.3,
    "v": 421207
  },
  {
    "t": "2024-02-02T14:15:00+05:30",
    "o": 1694.9,
    "h": 1698.65,
    "l": 1689.25,
    "c": 1693.85,
    "v": 1309687
  },
  {
    "t": "2024-02-02T13:15:00+05:30",
    "o": 1689.4,
    "h": 1696.6,
    "l": 1684,
    "c": 1694.9,
    "v": 572559
  },
  {
    "t": "2024-02-02T12:15:00+05:30",
    "o": 1710.95,
    "h": 1713.1,
    "l": 1688.9,
    "c": 1689.45,
    "v": 1767155
  },
  {
    "t": "2024-02-02T11:15:00+05:30",
    "o": 1700,
    "h": 1718.5,
    "l": 1698.55,
    "c": 1711.5,
    "v": 1601185
  },
  {
    "t": "2024-02-02T10:15:00+05:30",
    "o": 1694.4,
    "h": 1700.5,
    "l": 1694.05,
    "c": 1700,
    "v": 902967
  },
  {
    "t": "2024-02-02T09:15:00+05:30",
    "o": 1666.3,
    "h": 1698,
    "l": 1665,
    "c": 1694.5,
    "v": 1254399
  },
  {
    "t": "2024-02-01T15:15:00+05:30",
    "o": 1655.2,
    "h": 1658.75,
    "l": 1652.65,
    "c": 1655,
    "v": 641311
  },
  {
    "t": "2024-02-01T14:15:00+05:30",
    "o": 1660.9,
    "h": 1663.1,
    "l": 1655.2,
    "c": 1655.2,
    "v": 858388
  },
  {
    "t": "2024-02-01T13:15:00+05:30",
    "o": 1660.6,
    "h": 1665.1,
    "l": 1657,
    "c": 1660.9,
    "v": 396695
  },
  {
    "t": "2024-02-01T12:15:00+05:30",
    "o": 1659.3,
    "h": 1665,
    "l": 1656.25,
    "c": 1660.6,
    "v": 506274
  },
  {
    "t": "2024-02-01T11:15:00+05:30",
    "o": 1669.45,
    "h": 1670,
    "l": 1657.2,
    "c": 1659.6,
    "v": 986026
  },
  {
    "t": "2024-02-01T10:15:00+05:30",
    "o": 1671.85,
    "h": 1677,
    "l": 1668.65,
    "c": 1669.4,
    "v": 892462
  },
  {
    "t": "2024-02-01T09:15:00+05:30",
    "o": 1659.55,
    "h": 1674,
    "l": 1650.35,
    "c": 1672.1,
    "v": 1414081
  },
  {
    "t": "2024-01-31T15:15:00+05:30",
    "o": 1661.55,
    "h": 1667.25,
    "l": 1658.55,
    "c": 1660.05,
    "v": 1150846
  },
  {
    "t": "2024-01-31T14:15:00+05:30",
    "o": 1654.95,
    "h": 1661.55,
    "l": 1650,
    "c": 1661.55,
    "v": 1908663
  },
  {
    "t": "2024-01-31T13:15:00+05:30",
    "o": 1659,
    "h": 1661.4,
    "l": 1651.4,
    "c": 1654.7,
    "v": 490618
  },
  {
    "t": "2024-01-31T12:15:00+05:30",
    "o": 1665.05,
    "h": 1665.3,
    "l": 1656.2,
    "c": 1659,
    "v": 409062
  },
  {
    "t": "2024-01-31T11:15:00+05:30",
    "o": 1659.1,
    "h": 1665.8,
    "l": 1653.8,
    "c": 1665.05,
    "v": 943511
  },
  {
    "t": "2024-01-31T10:15:00+05:30",
    "o": 1654.75,
    "h": 1660.35,
    "l": 1648.65,
    "c": 1659.1,
    "v": 545735
  },
  {
    "t": "2024-01-31T09:15:00+05:30",
    "o": 1649.8,
    "h": 1655.55,
    "l": 1638.1,
    "c": 1654.65,
    "v": 1283226
  },
  {
    "t": "2024-01-30T15:15:00+05:30",
    "o": 1651.05,
    "h": 1654.8,
    "l": 1649.4,
    "c": 1653.5,
    "v": 542199
  },
  {
    "t": "2024-01-30T14:15:00+05:30",
    "o": 1665.4,
    "h": 1665.45,
    "l": 1648.25,
    "c": 1651.1,
    "v": 1165011
  },
  {
    "t": "2024-01-30T13:15:00+05:30",
    "o": 1665.95,
    "h": 1666.8,
    "l": 1659.1,
    "c": 1665.4,
    "v": 575495
  },
  {
    "t": "2024-01-30T12:15:00+05:30",
    "o": 1672.9,
    "h": 1673.9,
    "l": 1664.9,
    "c": 1665.95,
    "v": 605444
  },
  {
    "t": "2024-01-30T11:15:00+05:30",
    "o": 1677.3,
    "h": 1679,
    "l": 1672.7,
    "c": 1672.9,
    "v": 591625
  },
  {
    "t": "2024-01-30T10:15:00+05:30",
    "o": 1685.65,
    "h": 1690,
    "l": 1676.35,
    "c": 1677.3,
    "v": 646383
  },
  {
    "t": "2024-01-30T09:15:00+05:30",
    "o": 1663.9,
    "h": 1685.65,
    "l": 1662.45,
    "c": 1685.65,
    "v": 825888
  },
  {
    "t": "2024-01-29T15:15:00+05:30",
    "o": 1655,
    "h": 1655.75,
    "l": 1651,
    "c": 1654.25,
    "v": 552901
  },
  {
    "t": "2024-01-29T14:15:00+05:30",
    "o": 1655.65,
    "h": 1662.35,
    "l": 1653.4,
    "c": 1655,
    "v": 956422
  },
  {
    "t": "2024-01-29T13:15:00+05:30",
    "o": 1657.9,
    "h": 1661.6,
    "l": 1655.2,
    "c": 1655.8,
    "v": 285272
  },
  {
    "t": "2024-01-29T12:15:00+05:30",
    "o": 1658,
    "h": 1662.5,
    "l": 1656.1,
    "c": 1657.9,
    "v": 426677
  },
  {
    "t": "2024-01-29T11:15:00+05:30",
    "o": 1651.5,
    "h": 1658.05,
    "l": 1647.6,
    "c": 1658,
    "v": 616675
  },
  {
    "t": "2024-01-29T10:15:00+05:30",
    "o": 1656.65,
    "h": 1659.65,
    "l": 1651.3,
    "c": 1651.5,
    "v": 465094
  },
  {
    "t": "2024-01-29T09:15:00+05:30",
    "o": 1665.15,
    "h": 1679.35,
    "l": 1654.1,
    "c": 1657.15,
    "v": 796224
  },
  {
    "t": "2024-01-25T15:15:00+05:30",
    "o": 1665.5,
    "h": 1673.35,
    "l": 1662,
    "c": 1666,
    "v": 996922
  },
  {
    "t": "2024-01-25T14:15:00+05:30",
    "o": 1667.2,
    "h": 1676.65,
    "l": 1664.35,
    "c": 1665.2,
    "v": 1571617
  },
  {
    "t": "2024-01-25T13:15:00+05:30",
    "o": 1667.8,
    "h": 1672.65,
    "l": 1666.2,
    "c": 1666.85,
    "v": 428789
  },
  {
    "t": "2024-01-25T12:15:00+05:30",
    "o": 1673.55,
    "h": 1680.55,
    "l": 1664.9,
    "c": 1667.8,
    "v": 1565476
  },
  {
    "t": "2024-01-25T11:15:00+05:30",
    "o": 1665.35,
    "h": 1676.9,
    "l": 1663,
    "c": 1674,
    "v": 1649761
  },
  {
    "t": "2024-01-25T10:15:00+05:30",
    "o": 1662.4,
    "h": 1666.2,
    "l": 1658,
    "c": 1665.4,
    "v": 1186037
  },
  {
    "t": "2024-01-25T09:15:00+05:30",
    "o": 1672.95,
    "h": 1672.95,
    "l": 1659.4,
    "c": 1662.4,
    "v": 1441816
  },
  {
    "t": "2024-01-24T15:15:00+05:30",
    "o": 1677.95,
    "h": 1678.85,
    "l": 1671,
    "c": 1671,
    "v": 1278894
  },
  {
    "t": "2024-01-24T14:15:00+05:30",
    "o": 1658.05,
    "h": 1680,
    "l": 1655.85,
    "c": 1677.95,
    "v": 2500552
  },
  {
    "t": "2024-01-24T13:15:00+05:30",
    "o": 1657.05,
    "h": 1660.85,
    "l": 1651.5,
    "c": 1658.5,
    "v": 1063624
  },
  {
    "t": "2024-01-24T12:15:00+05:30",
    "o": 1650.65,
    "h": 1657.8,
    "l": 1645,
    "c": 1657.05,
    "v": 799635
  },
  {
    "t": "2024-01-24T11:15:00+05:30",
    "o": 1649.8,
    "h": 1655.05,
    "l": 1645,
    "c": 1650.6,
    "v": 809815
  },
  {
    "t": "2024-01-24T10:15:00+05:30",
    "o": 1657.4,
    "h": 1661,
    "l": 1648,
    "c": 1649.95,
    "v": 790705
  },
  {
    "t": "2024-01-24T09:15:00+05:30",
    "o": 1659.9,
    "h": 1667.55,
    "l": 1651.5,
    "c": 1657.35,
    "v": 1700569
  },
  {
    "t": "2024-01-23T15:15:00+05:30",
    "o": 1638,
    "h": 1647.6,
    "l": 1637.85,
    "c": 1642,
    "v": 563495
  },
  {
    "t": "2024-01-23T14:15:00+05:30",
    "o": 1656.35,
    "h": 1661.55,
    "l": 1637.7,
    "c": 1638,
    "v": 3694562
  },
  {
    "t": "2024-01-23T13:15:00+05:30",
    "o": 1662.55,
    "h": 1664.8,
    "l": 1653.2,
    "c": 1656.4,
    "v": 902082
  },
  {
    "t": "2024-01-23T12:15:00+05:30",
    "o": 1663,
    "h": 1667.8,
    "l": 1658.6,
    "c": 1663.05,
    "v": 647400
  },
  {
    "t": "2024-01-23T11:15:00+05:30",
    "o": 1670.65,
    "h": 1672.7,
    "l": 1660.1,
    "c": 1663,
    "v": 764496
  },
  {
    "t": "2024-01-23T10:15:00+05:30",
    "o": 1669.4,
    "h": 1674.7,
    "l": 1662.05,
    "c": 1670.65,
    "v": 801763
  },
  {
    "t": "2024-01-23T09:15:00+05:30",
    "o": 1650.1,
    "h": 1670.85,
    "l": 1650.1,
    "c": 1669.8,
    "v": 1774225
  },
  {
    "t": "2024-01-20T15:15:00+05:30",
    "o": 1649.75,
    "h": 1651,
    "l": 1648.95,
    "c": 1649.45,
    "v": 112145
  },
  {
    "t": "2024-01-20T14:15:00+05:30",
    "o": 1646.95,
    "h": 1650,
    "l": 1645,
    "c": 1649.65,
    "v": 266840
  },
  {
    "t": "2024-01-20T13:15:00+05:30",
    "o": 1650,
    "h": 1651.6,
    "l": 1645.25,
    "c": 1646.95,
    "v": 150662
  },
  {
    "t": "2024-01-20T12:15:00+05:30",
    "o": 1652.55,
    "h": 1653.7,
    "l": 1645,
    "c": 1650,
    "v": 146927
  },
  {
    "t": "2024-01-20T11:15:00+05:30",
    "o": 1653.8,
    "h": 1655.75,
    "l": 1651,
    "c": 1652.4,
    "v": 104827
  },
  {
    "t": "2024-01-20T10:15:00+05:30",
    "o": 1658.8,
    "h": 1659.45,
    "l": 1653.4,
    "c": 1653.8,
    "v": 123149
  },
  {
    "t": "2024-01-20T09:15:00+05:30",
    "o": 1665.55,
    "h": 1669.25,
    "l": 1655.15,
    "c": 1658.85,
    "v": 244753
  },
  {
    "t": "2024-01-19T15:15:00+05:30",
    "o": 1658.65,
    "h": 1660.8,
    "l": 1655,
    "c": 1657.85,
    "v": 658145
  },
  {
    "t": "2024-01-19T14:15:00+05:30",
    "o": 1660.45,
    "h": 1662.55,
    "l": 1655.5,
    "c": 1658.6,
    "v": 1129568
  },
  {
    "t": "2024-01-19T13:15:00+05:30",
    "o": 1657.55,
    "h": 1661,
    "l": 1655.85,
    "c": 1660.4,
    "v": 599886
  },
  {
    "t": "2024-01-19T12:15:00+05:30",
    "o": 1649.15,
    "h": 1658,
    "l": 1648.05,
    "c": 1657.55,
    "v": 482267
  },
  {
    "t": "2024-01-19T11:15:00+05:30",
    "o": 1650.35,
    "h": 1650.95,
    "l": 1644.15,
    "c": 1649.15,
    "v": 436310
  },
  {
    "t": "2024-01-19T10:15:00+05:30",
    "o": 1653,
    "h": 1657.2,
    "l": 1650.2,
    "c": 1650.2,
    "v": 384284
  },
  {
    "t": "2024-01-19T09:15:00+05:30",
    "o": 1651.6,
    "h": 1665.5,
    "l": 1650,
    "c": 1653,
    "v": 809816
  }
]