[
  {
    "t": "2024-06-21T15:15:00+05:30",
    "o": 1451.1,
    "h": 1460.1,
    "l": 1450,
    "c": 1455.5,
    "v": 6409096
  },
  {
    "t": "2024-06-21T14:15:00+05:30",
    "o": 1453.5,
    "h": 1458,
    "l": 1440.6,
    "c": 1451,
    "v": 12658356
  },
  {
    "t": "2024-06-21T13:15:00+05:30",
    "o": 1450.35,
    "h": 1454.5,
    "l": 1449.2,
    "c": 1453.5,
    "v": 2226920
  },
  {
    "t": "2024-06-21T12:15:00+05:30",
    "o": 1458.65,
    "h": 1458.7,
    "l": 1444.4,
    "c": 1449.95,
    "v": 2903128
  },
  {
    "t": "2024-06-21T11:15:00+05:30",
    "o": 1458.1,
    "h": 1459.85,
    "l": 1455.5,
    "c": 1458.65,
    "v": 1502274
  },
  {
    "t": "2024-06-21T10:15:00+05:30",
    "o": 1461.55,
    "h": 1465.5,
    "l": 1456,
    "c": 1458.1,
    "v": 2490274
  },
  {
    "t": "2024-06-21T09:15:00+05:30",
    "o": 1473.6,
    "h": 1474.7,
    "l": 1460,
    "c": 1461.65,
    "v": 2911380
  },
  {
    "t": "2024-06-20T15:15:00+05:30",
    "o": 1473.85,
    "h": 1475.3,
    "l": 1471.5,
    "c": 1474.5,
    "v": 1130870
  },
  {
    "t": "2024-06-20T14:15:00+05:30",
    "o": 1476.6,
    "h": 1481.45,
    "l": 1470.45,
    "c": 1473.3,
    "v": 3995758
  },
  {
    "t": "2024-06-20T13:15:00+05:30",
    "o": 1478.2,
    "h": 1482.85,
    "l": 1473.3,
    "c": 1476.45,
    "v": 2642630
  },
  {
    "t": "2024-06-20T12:15:00+05:30",
    "o": 1475.15,
    "h": 1481.5,
    "l": 1474.5,
    "c": 1478.2,
    "v": 1189650
  },
  {
    "t": "2024-06-20T11:15:00+05:30",
    "o": 1475.5,
    "h": 1477.25,
    "l": 1471,
    "c": 1475.1,
    "v": 887254
  },
  {
    "t": "2024-06-20T10:15:00+05:30",
    "o": 1467.4,
    "h": 1481.8,
    "l": 1466.75,
    "c": 1475.5,
    "v": 2387426
  },
  {
    "t": "2024-06-20T09:15:00+05:30",
    "o": 1459,
    "h": 1472.2,
    "l": 1450.1,
    "c": 1467.5,
    "v": 3778754
  },
  {
    "t": "2024-06-19T15:15:00+05:30",
    "o": 1457.5,
    "h": 1460.75,
    "l": 1456.5,
    "c": 1458.5,
    "v": 2015132
  },
  {
    "t": "2024-06-19T14:15:00+05:30",
    "o": 1459.4,
    "h": 1468,
    "l": 1456,
    "c": 1457.8,
    "v": 3512072
  },
  {
    "t": "2024-06-19T13:15:00+05:30",
    "o": 1469.5,
    "h": 1470.5,
    "l": 1458,
    "c": 1459.7,
    "v": 2327220
  },
  {
    "t": "2024-06-19T12:15:00+05:30",
    "o": 1471.7,
    "h": 1473.5,
    "l": 1469,
    "c": 1469.5,
    "v": 1613080
  },
  {
    "t": "2024-06-19T11:15:00+05:30",
    "o": 1467.7,
    "h": 1472.35,
    "l": 1467,
    "c": 1471.7,
    "v": 1528108
  },
  {
    "t": "2024-06-19T10:15:00+05:30",
    "o": 1472.7,
    "h": 1473.3,
    "l": 1459.9,
    "c": 1467.7,
    "v": 3149248
  },
  {
    "t": "2024-06-19T09:15:00+05:30",
    "o": 1487.5,
    "h": 1487.5,
    "l": 1472.7,
    "c": 1472.7,
    "v": 2990868
  },
  {
    "t": "2024-06-18T15:15:00+05:30",
    "o": 1481.9,
    "h": 1482,
    "l": 1478.6,
    "c": 1479.95,
    "v": 872868
  },
  {
    "t": "2024-06-18T14:15:00+05:30",
    "o": 1475.1,
    "h": 1482.1,
    "l": 1474.05,
    "c": 1481.9,
    "v": 1581996
  },
  {
    "t": "2024-06-18T13:15:00+05:30",
    "o": 1474.4,
    "h": 1475.95,
    "l": 1472.2,
    "c": 1475.2,
    "v": 544542
  },
  {
    "t": "2024-06-18T12:15:00+05:30",
    "o": 1476,
    "h": 1477,
    "l": 1473.7,
    "c": 1474.45,
    "v": 620460
  },
  {
    "t": "2024-06-18T11:15:00+05:30",
    "o": 1478.25,
    "h": 1481.35,
    "l": 1475.5,
    "c": 1476,
    "v": 523042
  },
  {
    "t": "2024-06-18T10:15:00+05:30",
    "o": 1479.3,
    "h": 1482.5,
    "l": 1477.1,
    "c": 1478.25,
    "v": 746082
  },
  {
    "t": "2024-06-18T09:15:00+05:30",
    "o": 1487.35,
    "h": 1487.4,
    "l": 1471.35,
    "c": 1479.3,
    "v": 2164586
  },
  {
    "t": "2024-06-14T15:15:00+05:30",
    "o": 1477.75,
    "h": 1478.25,
    "l": 1475.5,
    "c": 1475.7,
    "v": 1066808
  },
  {
    "t": "2024-06-14T14:15:00+05:30",
    "o": 1476,
    "h": 1479.7,
    "l": 1474.5,
    "c": 1477.75,
    "v": 2084416
  },
  {
    "t": "2024-06-14T13:15:00+05:30",
    "o": 1476.5,
    "h": 1477.45,
    "l": 1473.15,
    "c": 1476,
    "v": 886872
  },
  {
    "t": "2024-06-14T12:15:00+05:30",
    "o": 1470,
    "h": 1477.45,
    "l": 1469.7,
    "c": 1476.5,
    "v": 710452
  },
  {
    "t": "2024-06-14T11:15:00+05:30",
    "o": 1472.75,
    "h": 1473,
    "l": 1467.5,
    "c": 1470,
    "v": 608642
  },
  {
    "t": "2024-06-14T10:15:00+05:30",
    "o": 1466.6,
    "h": 1473.9,
    "l": 1465.15,
    "c": 1473,
    "v": 1258202
  },
  {
    "t": "2024-06-14T09:15:00+05:30",
    "o": 1470,
    "h": 1470.5,
    "l": 1457.2,
    "c": 1466.6,
    "v": 1459314
  },
  {
    "t": "2024-06-13T15:15:00+05:30",
    "o": 1464.4,
    "h": 1464.9,
    "l": 1463.5,
    "c": 1463.8,
    "v": 825366
  },
  {
    "t": "2024-06-13T14:15:00+05:30",
    "o": 1469,
    "h": 1471,
    "l": 1464.3,
    "c": 1464.45,
    "v": 2555160
  },
  {
    "t": "2024-06-13T13:15:00+05:30",
    "o": 1468.5,
    "h": 1469.95,
    "l": 1466,
    "c": 1469,
    "v": 1103384
  },
  {
    "t": "2024-06-13T12:15:00+05:30",
    "o": 1466,
    "h": 1468.95,
    "l": 1466,
    "c": 1468.5,
    "v": 927660
  },
  {
    "t": "2024-06-13T11:15:00+05:30",
    "o": 1464.4,
    "h": 1466.25,
    "l": 1461.55,
    "c": 1466,
    "v": 570228
  },
  {
    "t": "2024-06-13T10:15:00+05:30",
    "o": 1467.2,
    "h": 1467.2,
    "l": 1464.05,
    "c": 1464.4,
    "v": 1021528
  },
  {
    "t": "2024-06-13T09:15:00+05:30",
    "o": 1472,
    "h": 1472.25,
    "l": 1460.1,
    "c": 1467,
    "v": 1979304
  },
  {
    "t": "2024-06-12T15:15:00+05:30",
    "o": 1462.65,
    "h": 1465.3,
    "l": 1459.75,
    "c": 1462.25,
    "v": 1105170
  },
  {
    "t": "2024-06-12T14:15:00+05:30",
    "o": 1466.25,
    "h": 1469,
    "l": 1462.55,
    "c": 1462.6,
    "v": 1556670
  },
  {
    "t": "2024-06-12T13:15:00+05:30",
    "o": 1473.85,
    "h": 1474.7,
    "l": 1465,
    "c": 1466.5,
    "v": 948240
  },
  {
    "t": "2024-06-12T12:15:00+05:30",
    "o": 1469,
    "h": 1476,
    "l": 1468.5,
    "c": 1474.1,
    "v": 1244540
  },
  {
    "t": "2024-06-12T11:15:00+05:30",
    "o": 1467.25,
    "h": 1471,
    "l": 1464,
    "c": 1468.7,
    "v": 944778
  },
  {
    "t": "2024-06-12T10:15:00+05:30",
    "o": 1466,
    "h": 1474.5,
    "l": 1464.9,
    "c": 1467.25,
    "v": 1622662
  },
  {
    "t": "2024-06-12T09:15:00+05:30",
    "o": 1457.5,
    "h": 1469.5,
    "l": 1455.2,
    "c": 1466,
    "v": 2564194
  },
  {
    "t": "2024-06-11T15:15:00+05:30",
    "o": 1455.6,
    "h": 1458,
    "l": 1454.7,
    "c": 1457.5,
    "v": 1121894
  },
  {
    "t": "2024-06-11T14:15:00+05:30",
    "o": 1462.3,
    "h": 1462.95,
    "l": 1455,
    "c": 1455.6,
    "v": 2381462
  },
  {
    "t": "2024-06-11T13:15:00+05:30",
    "o": 1462.8,
    "h": 1467.5,
    "l": 1461,
    "c": 1462.3,
    "v": 1118602
  },
  {
    "t": "2024-06-11T12:15:00+05:30",
    "o": 1468,
    "h": 1468,
    "l": 1462,
    "c": 1462.2,
    "v": 1116346
  },
  {
    "t": "2024-06-11T11:15:00+05:30",
    "o": 1469,
    "h": 1470.7,
    "l": 1466.25,
    "c": 1468,
    "v": 1443712
  },
  {
    "t": "2024-06-11T10:15:00+05:30",
    "o": 1466,
    "h": 1470.85,
    "l": 1465.15,
    "c": 1469,
    "v": 997500
  },
  {
    "t": "2024-06-11T09:15:00+05:30",
    "o": 1469,
    "h": 1473.7,
    "l": 1456.5,
    "c": 1466,
    "v": 3202542
  },
  {
    "t": "2024-06-10T15:15:00+05:30",
    "o": 1470.6,
    "h": 1472.85,
    "l": 1468.5,
    "c": 1472,
    "v": 494166
  },
  {
    "t": "2024-06-10T14:15:00+05:30",
    "o": 1481,
    "h": 1481.3,
    "l": 1468.35,
    "c": 1470.3,
    "v": 1374570
  },
  {
    "t": "2024-06-10T13:15:00+05:30",
    "o": 1480.7,
    "h": 1482.9,
    "l": 1478.6,
    "c": 1481.1,
    "v": 887986
  },
  {
    "t": "2024-06-10T12:15:00+05:30",
    "o": 1478.5,
    "h": 1485,
    "l": 1476.45,
    "c": 1480.7,
    "v": 847144
  },
  {
    "t": "2024-06-10T11:15:00+05:30",
    "o": 1480.5,
    "h": 1483.25,
    "l": 1476.1,
    "c": 1478.4,
    "v": 783710
  },
  {
    "t": "2024-06-10T10:15:00+05:30",
    "o": 1481.7,
    "h": 1486.25,
    "l": 1478.05,
    "c": 1480.5,
    "v": 788632
  },
  {
    "t": "2024-06-10T09:15:00+05:30",
    "o": 1469.95,
    "h": 1493.35,
    "l": 1468.1,
    "c": 1481.7,
    "v": 3958224
  },
  {
    "t": "2024-06-07T15:15:00+05:30",
    "o": 1470.45,
    "h": 1471.25,
    "l": 1463,
    "c": 1464,
    "v": 1669694
  },
  {
    "t": "2024-06-07T14:15:00+05:30",
    "o": 1464.4,
    "h": 1472,
    "l": 1464.1,
    "c": 1470.95,
    "v": 5355566
  },
  {
    "t": "2024-06-07T13:15:00+05:30",
    "o": 1460.6,
    "h": 1471,
    "l": 1455.8,
    "c": 1464.4,
    "v": 2536306
  },
  {
    "t": "2024-06-07T12:15:00+05:30",
    "o": 1463,
    "h": 1465.9,
    "l": 1456.35,
    "c": 1460.7,
    "v": 1510768
  },
  {
    "t": "2024-06-07T11:15:00+05:30",
    "o": 1445.55,
    "h": 1464.35,
    "l": 1439.5,
    "c": 1463,
    "v": 3555178
  },
  {
    "t": "2024-06-07T10:15:00+05:30",
    "o": 1441.2,
    "h": 1447,
    "l": 1438.1,
    "c": 1445.8,
    "v": 1567016
  },
  {
    "t": "2024-06-07T09:15:00+05:30",
    "o": 1428.5,
    "h": 1443.5,
    "l": 1426.5,
    "c": 1441.2,
    "v": 2258152
  },
  {
    "t": "2024-06-06T15:15:00+05:30",
    "o": 1431.45,
    "h": 1438.8,
    "l": 1430.9,
    "c": 1436,
    "v": 1822012
  },
  {
    "t": "2024-06-06T14:15:00+05:30",
    "o": 1430.35,
    "h": 1432.5,
    "l": 1421.9,
    "c": 1431.5,
    "v": 5223936
  },
  {
    "t": "2024-06-06T13:15:00+05:30",
    "o": 1426.3,
    "h": 1438,
    "l": 1425.5,
    "c": 1430.35,
    "v": 2256736
  },
  {
    "t": "2024-06-06T12:15:00+05:30",
    "o": 1424.4,
    "h": 1431,
    "l": 1423.1,
    "c": 1426.3,
    "v": 1314462
  },
  {
    "t": "2024-06-06T11:15:00+05:30",
    "o": 1439.8,
    "h": 1439.9,
    "l": 1422.5,
    "c": 1424.4,
    "v": 2110882
  },
  {
    "t": "2024-06-06T10:15:00+05:30",
    "o": 1432.4,
    "h": 1443.7,
    "l": 1431.8,
    "c": 1439.8,
    "v": 1562402
  },
  {
    "t": "2024-06-06T09:15:00+05:30",
    "o": 1435,
    "h": 1437.5,
    "l": 1421.35,
    "c": 1432.1,
    "v": 3413782
  },
  {
    "t": "2024-06-05T15:15:00+05:30",
    "o": 1421.7,
    "h": 1423.2,
    "l": 1416.5,
    "c": 1419,
    "v": 1492162
  },
  {
    "t": "2024-06-05T14:15:00+05:30",
    "o": 1413.6,
    "h": 1424.5,
    "l": 1411,
    "c": 1421.65,
    "v": 2838972
  },
  {
    "t": "2024-06-05T13:15:00+05:30",
    "o": 1413,
    "h": 1422.9,
    "l": 1410.7,
    "c": 1413.6,
    "v": 1295428
  },
  {
    "t": "2024-06-05T12:15:00+05:30",
    "o": 1411,
    "h": 1416.9,
    "l": 1403.6,
    "c": 1413.1,
    "v": 1263018
  },
  {
    "t": "2024-06-05T11:15:00+05:30",
    "o": 1415.15,
    "h": 1431.15,
    "l": 1404.3,
    "c": 1411.7,
    "v": 2583054
  },
  {
    "t": "2024-06-05T10:15:00+05:30",
    "o": 1402.7,
    "h": 1416.9,
    "l": 1390.5,
    "c": 1415.3,
    "v": 2346870
  },
  {
    "t": "2024-06-05T09:15:00+05:30",
    "o": 1422,
    "h": 1422,
    "l": 1384.1,
    "c": 1402.7,
    "v": 5428164
  },
  {
    "t": "2024-06-04T15:15:00+05:30",
    "o": 1399.5,
    "h": 1416.25,
    "l": 1394.1,
    "c": 1416.25,
    "v": 2367662
  },
  {
    "t": "2024-06-04T14:15:00+05:30",
    "o": 1413.7,
    "h": 1413.75,
    "l": 1382.5,
    "c": 1399.6,
    "v": 4816146
  },
  {
    "t": "2024-06-04T13:15:00+05:30",
    "o": 1403.75,
    "h": 1427.8,
    "l": 1402.5,
    "c": 1412.8,
    "v": 4830456
  },
  {
    "t": "2024-06-04T12:15:00+05:30",
    "o": 1374.9,
    "h": 1410,
    "l": 1359.3,
    "c": 1403.9,
    "v": 5297534
  },
  {
    "t": "2024-06-04T11:15:00+05:30",
    "o": 1403.7,
    "h": 1433,
    "l": 1365.8,
    "c": 1374.9,
    "v": 6123950
  },
  {
    "t": "2024-06-04T10:15:00+05:30",
    "o": 1472.25,
    "h": 1473,
    "l": 1398,
    "c": 1403.6,
    "v": 5462130
  },
  {
    "t": "2024-06-04T09:15:00+05:30",
    "o": 1498.05,
    "h": 1498.05,
    "l": 1441.1,
    "c": 1472.1,
    "v": 7410078
  },
  {
    "t": "2024-06-03T15:15:00+05:30",
    "o": 1511.5,
    "h": 1514.5,
    "l": 1508.8,
    "c": 1514,
    "v": 1746684
  },
  {
    "t": "2024-06-03T14:15:00+05:30",
    "o": 1507.5,
    "h": 1512.5,
    "l": 1502.25,
    "c": 1512,
    "v": 3614630
  },
  {
    "t": "2024-06-03T13:15:00+05:30",
    "o": 1487.15,
    "h": 1510,
    "l": 1486,
    "c": 1507.4,
    "v": 4365720
  },
  {
    "t": "2024-06-03T12:15:00+05:30",
    "o": 1482.1,
    "h": 1489.95,
    "l": 1481.5,
    "c": 1487.25,
    "v": 1529982
  },
  {
    "t": "2024-06-03T11:15:00+05:30",
    "o": 1490,
    "h": 1492.5,
    "l": 1480.7,
    "c": 1482.2,
    "v": 2138210
  },
  {
    "t": "2024-06-03T10:15:00+05:30",
    "o": 1477.1,
    "h": 1490.85,
    "l": 1474.2,
    "c": 1489.95,
    "v": 2451092
  },
  {
    "t": "2024-06-03T09:15:00+05:30",
    "o": 1483,
    "h": 1483.95,
    "l": 1459,
    "c": 1477.25,
    "v": 5442368
  },
  {
    "t": "2024-05-31T15:15:00+05:30",
    "o": 1434.5,
    "h": 1434.9,
    "l": 1426.05,
    "c": 1429.5,
    "v": 5961024
  },
  {
    "t": "2024-05-31T14:15:00+05:30",
    "o": 1430,
    "h": 1435.7,
    "l": 1422.5,
    "c": 1434.2,
    "v": 9767038
  },
  {
    "t": "2024-05-31T13:15:00+05:30",
    "o": 1429.45,
    "h": 1432.7,
    "l": 1428,
    "c": 1430,
    "v": 2817852
  },
  {
    "t": "2024-05-31T12:15:00+05:30",
    "o": 1425.9,
    "h": 1431.3,
    "l": 1422.25,
    "c": 1429.4,
    "v": 4413522
  },
  {
    "t": "2024-05-31T11:15:00+05:30",
    "o": 1425.75,
    "h": 1428.2,
    "l": 1423.6,
    "c": 1425.9,
    "v": 1529324
  },
  {
    "t": "2024-05-31T10:15:00+05:30",
    "o": 1431.85,
    "h": 1435.85,
    "l": 1423.5,
    "c": 1425.5,
    "v": 2530642
  },
  {
    "t": "2024-05-31T09:15:00+05:30",
    "o": 1431.3,
    "h": 1442.25,
    "l": 1430,
    "c": 1431.85,
    "v": 3870840
  },
  {
    "t": "2024-05-30T15:15:00+05:30",
    "o": 1422.2,
    "h": 1432,
    "l": 1420.7,
    "c": 1429.55,
    "v": 1867624
  },
  {
    "t": "2024-05-30T14:15:00+05:30",
    "o": 1424.5,
    "h": 1427.7,
    "l": 1420.1,
    "c": 1422.2,
    "v": 4011164
  },
  {
    "t": "2024-05-30T13:15:00+05:30",
    "o": 1428.5,
    "h": 1429.2,
    "l": 1421.4,
    "c": 1424.5,
    "v": 1624502
  },
  {
    "t": "2024-05-30T12:15:00+05:30",
    "o": 1428.5,
    "h": 1432,
    "l": 1425.25,
    "c": 1428.5,
    "v": 949904
  },
  {
    "t": "2024-05-30T11:15:00+05:30",
    "o": 1428.15,
    "h": 1429.2,
    "l": 1425.05,
    "c": 1428.3,
    "v": 535894
  },
  {
    "t": "2024-05-30T10:15:00+05:30",
    "o": 1426.25,
    "h": 1429.75,
    "l": 1423.9,
    "c": 1428.15,
    "v": 1516172
  },
  {
    "t": "2024-05-30T09:15:00+05:30",
    "o": 1435.5,
    "h": 1440.4,
    "l": 1425.65,
    "c": 1426.15,
    "v": 2500536
  },
  {
    "t": "2024-05-29T15:15:00+05:30",
    "o": 1440.95,
    "h": 1441,
    "l": 1438.45,
    "c": 1440.5,
    "v": 1044348
  },
  {
    "t": "2024-05-29T14:15:00+05:30",
    "o": 1446.5,
    "h": 1446.85,
    "l": 1438.6,
    "c": 1440.95,
    "v": 1797516
  },
  {
    "t": "2024-05-29T13:15:00+05:30",
    "o": 1446.05,
    "h": 1448,
    "l": 1444.1,
    "c": 1446.2,
    "v": 626002
  },
  {
    "t": "2024-05-29T12:15:00+05:30",
    "o": 1445.4,
    "h": 1449.3,
    "l": 1443.05,
    "c": 1446.5,
    "v": 879134
  },
  {
    "t": "2024-05-29T11:15:00+05:30",
    "o": 1447.3,
    "h": 1447.7,
    "l": 1442.75,
    "c": 1445.4,
    "v": 576352
  },
  {
    "t": "2024-05-29T10:15:00+05:30",
    "o": 1450,
    "h": 1452,
    "l": 1446.7,
    "c": 1447.3,
    "v": 1055512
  },
  {
    "t": "2024-05-29T09:15:00+05:30",
    "o": 1446.5,
    "h": 1458,
    "l": 1446.5,
    "c": 1450,
    "v": 1288148
  },
  {
    "t": "2024-05-28T15:15:00+05:30",
    "o": 1457.1,
    "h": 1457.1,
    "l": 1452.75,
    "c": 1455.5,
    "v": 1012896
  },
  {
    "t": "2024-05-28T14:15:00+05:30",
    "o": 1462.5,
    "h": 1463.3,
    "l": 1456.5,
    "c": 1457.1,
    "v": 1642876
  },
  {
    "t": "2024-05-28T13:15:00+05:30",
    "o": 1464.2,
    "h": 1466.35,
    "l": 1461.05,
    "c": 1462.5,
    "v": 1006946
  },
  {
    "t": "2024-05-28T12:15:00+05:30",
    "o": 1469.4,
    "h": 1471.9,
    "l": 1462.65,
    "c": 1464.7,
    "v": 957878
  },
  {
    "t": "2024-05-28T11:15:00+05:30",
    "o": 1470.9,
    "h": 1473,
    "l": 1466.6,
    "c": 1469.4,
    "v": 541866
  },
  {
    "t": "2024-05-28T10:15:00+05:30",
    "o": 1473.15,
    "h": 1478.5,
    "l": 1468.1,
    "c": 1470.75,
    "v": 1140370
  },
  {
    "t": "2024-05-28T09:15:00+05:30",
    "o": 1468,
    "h": 1474.95,
    "l": 1468,
    "c": 1473.1,
    "v": 1487042
  },
  {
    "t": "2024-05-27T15:15:00+05:30",
    "o": 1466.95,
    "h": 1469.3,
    "l": 1465,
    "c": 1467.45,
    "v": 513532
  },
  {
    "t": "2024-05-27T14:15:00+05:30",
    "o": 1477.5,
    "h": 1477.5,
    "l": 1461.55,
    "c": 1466.7,
    "v": 1278462
  },
  {
    "t": "2024-05-27T13:15:00+05:30",
    "o": 1476.5,
    "h": 1478.5,
    "l": 1473.4,
    "c": 1477.5,
    "v": 439696
  },
  {
    "t": "2024-05-27T12:15:00+05:30",
    "o": 1474.25,
    "h": 1478.9,
    "l": 1473.2,
    "c": 1476.5,
    "v": 758944
  },
  {
    "t": "2024-05-27T11:15:00+05:30",
    "o": 1468.3,
    "h": 1475,
    "l": 1467,
    "c": 1474.1,
    "v": 1178986
  },
  {
    "t": "2024-05-27T10:15:00+05:30",
    "o": 1468.35,
    "h": 1472.7,
    "l": 1465.1,
    "c": 1468.3,
    "v": 802954
  },
  {
    "t": "2024-05-27T09:15:00+05:30",
    "o": 1480.2,
    "h": 1484.9,
    "l": 1468.1,
    "c": 1468.35,
    "v": 1593396
  },
  {
    "t": "2024-05-24T15:15:00+05:30",
    "o": 1481.1,
    "h": 1481.9,
    "l": 1478.5,
    "c": 1479.5,
    "v": 810938
  },
  {
    "t": "2024-05-24T14:15:00+05:30",
    "o": 1480.4,
    "h": 1483,
    "l": 1477.3,
    "c": 1481.15,
    "v": 1757622
  },
  {
    "t": "2024-05-24T13:15:00+05:30",
    "o": 1483,
    "h": 1485.55,
    "l": 1480,
    "c": 1480.4,
    "v": 789634
  },
  {
    "t": "2024-05-24T12:15:00+05:30",
    "o": 1482.2,
    "h": 1486,
    "l": 1480.3,
    "c": 1482.6,
    "v": 781740
  },
  {
    "t": "2024-05-24T11:15:00+05:30",
    "o": 1480.5,
    "h": 1484,
    "l": 1479,
    "c": 1482.2,
    "v": 438198
  },
  {
    "t": "2024-05-24T10:15:00+05:30",
    "o": 1476.1,
    "h": 1483,
    "l": 1476.1,
    "c": 1480,
    "v": 675904
  },
  {
    "t": "2024-05-24T09:15:00+05:30",
    "o": 1483.6,
    "h": 1488.5,
    "l": 1476.1,
    "c": 1476.2,
    "v": 1788226
  },
  {
    "t": "2024-05-23T15:15:00+05:30",
    "o": 1487.05,
    "h": 1492.2,
    "l": 1482.5,
    "c": 1484.6,
    "v": 1983604
  },
  {
    "t": "2024-05-23T14:15:00+05:30",
    "o": 1482.75,
    "h": 1487.5,
    "l": 1481,
    "c": 1487.25,
    "v": 4732938
  },
  {
    "t": "2024-05-23T13:15:00+05:30",
    "o": 1472,
    "h": 1483.25,
    "l": 1470.4,
    "c": 1482.75,
    "v": 3438148
  },
  {
    "t": "2024-05-23T12:15:00+05:30",
    "o": 1467.7,
    "h": 1473.75,
    "l": 1465.9,
    "c": 1471.65,
    "v": 1086284
  },
  {
    "t": "2024-05-23T11:15:00+05:30",
    "o": 1466,
    "h": 1469.6,
    "l": 1465.5,
    "c": 1467.8,
    "v": 491358
  },
  {
    "t": "2024-05-23T10:15:00+05:30",
    "o": 1467.6,
    "h": 1470.5,
    "l": 1464.05,
    "c": 1466.25,
    "v": 979926
  },
  {
    "t": "2024-05-23T09:15:00+05:30",
    "o": 1458.55,
    "h": 1471.25,
    "l": 1455,
    "c": 1467.8,
    "v": 1818560
  },
  {
    "t": "2024-05-22T15:15:00+05:30",
    "o": 1460.1,
    "h": 1461,
    "l": 1457.9,
    "c": 1460,
    "v": 663126
  },
  {
    "t": "2024-05-22T14:15:00+05:30",
    "o": 1463.7,
    "h": 1465,
    "l": 1459.25,
    "c": 1460.1,
    "v": 1341864
  },
  {
    "t": "2024-05-22T13:15:00+05:30",
    "o": 1464.8,
    "h": 1468.8,
    "l": 1460.5,
    "c": 1463.6,
    "v": 1266808
  },
  {
    "t": "2024-05-22T12:15:00+05:30",
    "o": 1460.9,
    "h": 1466.5,
    "l": 1460,
    "c": 1464.8,
    "v": 1282936
  },
  {
    "t": "2024-05-22T11:15:00+05:30",
    "o": 1458,
    "h": 1461.8,
    "l": 1455,
    "c": 1460.85,
    "v": 710400
  },
  {
    "t": "2024-05-22T10:15:00+05:30",
    "o": 1459.25,
    "h": 1462.4,
    "l": 1456,
    "c": 1458,
    "v": 1131304
  },
  {
    "t": "2024-05-22T09:15:00+05:30",
    "o": 1436.3,
    "h": 1465.5,
    "l": 1436.3,
    "c": 1459.6,
    "v": 3735382
  }
]