[
  {
    "t": "2024-12-24T15:15:00+05:30",
    "o": 1221.85,
    "h": 1224.5,
    "l": 1221.5,
    "c": 1224.2,
    "v": 413766
  },
  {
    "t": "2024-12-24T15:00:00+05:30",
    "o": 1223.3,
    "h": 1223.4,
    "l": 1221,
    "c": 1221.85,
    "v": 320460
  },
  {
    "t": "2024-12-24T14:45:00+05:30",
    "o": 1223.25,
    "h": 1225.3,
    "l": 1221.65,
    "c": 1223.3,
    "v": 318282
  },
  {
    "t": "2024-12-24T14:30:00+05:30",
    "o": 1224,
    "h": 1224.75,
    "l": 1222.05,
    "c": 1223.25,
    "v": 188381
  },
  {
    "t": "2024-12-24T14:15:00+05:30",
    "o": 1225.25,
    "h": 1225.65,
    "l": 1222.1,
    "c": 1224.35,
    "v": 235675
  },
  {
    "t": "2024-12-24T14:00:00+05:30",
    "o": 1224.65,
    "h": 1225.95,
    "l": 1223.05,
    "c": 1225.4,
    "v": 189054
  },
  {
    "t": "2024-12-24T13:45:00+05:30",
    "o": 1227.35,
    "h": 1227.55,
    "l": 1223.55,
    "c": 1224.6,
    "v": 342487
  },
  {
    "t": "2024-12-24T13:30:00+05:30",
    "o": 1229.1,
    "h": 1229.75,
    "l": 1226.85,
    "c": 1227.4,
    "v": 210296
  },
  {
    "t": "2024-12-24T13:15:00+05:30",
    "o": 1229,
    "h": 1230.6,
    "l": 1228.5,
    "c": 1229.1,
    "v": 246258
  },
  {
    "t": "2024-12-24T13:00:00+05:30",
    "o": 1228,
    "h": 1229.7,
    "l": 1227.85,
    "c": 1229,
    "v": 192391
  },
  {
    "t": "2024-12-24T12:45:00+05:30",
    "o": 1228.3,
    "h": 1229.9,
    "l": 1227.35,
    "c": 1228,
    "v": 186487
  },
  {
    "t": "2024-12-24T12:30:00+05:30",
    "o": 1227.25,
    "h": 1229,
    "l": 1226.25,
    "c": 1227.95,
    "v": 198289
  },
  {
    "t": "2024-12-24T12:15:00+05:30",
    "o": 1227.6,
    "h": 1227.95,
    "l": 1225.65,
    "c": 1227.3,
    "v": 228133
  },
  {
    "t": "2024-12-24T12:00:00+05:30",
    "o": 1229.5,
    "h": 1229.8,
    "l": 1227.1,
    "c": 1227.65,
    "v": 162926
  },
  {
    "t": "2024-12-24T11:45:00+05:30",
    "o": 1231.3,
    "h": 1232,
    "l": 1229.15,
    "c": 1229.55,
    "v": 200047
  },
  {
    "t": "2024-12-24T11:30:00+05:30",
    "o": 1232.45,
    "h": 1232.9,
    "l": 1230.4,
    "c": 1231.3,
    "v": 212085
  },
  {
    "t": "2024-12-24T11:15:00+05:30",
    "o": 1230.6,
    "h": 1232.6,
    "l": 1230.3,
    "c": 1232.45,
    "v": 157641
  },
  {
    "t": "2024-12-24T11:00:00+05:30",
    "o": 1230.2,
    "h": 1232.5,
    "l": 1230,
    "c": 1230.6,
    "v": 135691
  },
  {
    "t": "2024-12-24T10:45:00+05:30",
    "o": 1230.4,
    "h": 1232.1,
    "l": 1229.35,
    "c": 1230.2,
    "v": 161729
  },
  {
    "t": "2024-12-24T10:30:00+05:30",
    "o": 1230.85,
    "h": 1233.55,
    "l": 1230,
    "c": 1230.45,
    "v": 679827
  },
  {
    "t": "2024-12-24T10:15:00+05:30",
    "o": 1227.25,
    "h": 1231,
    "l": 1226.9,
    "c": 1230.85,
    "v": 305502
  },
  {
    "t": "2024-12-24T10:00:00+05:30",
    "o": 1228.65,
    "h": 1229.2,
    "l": 1227,
    "c": 1227.25,
    "v": 186254
  },
  {
    "t": "2024-12-24T09:45:00+05:30",
    "o": 1227.65,
    "h": 1229.05,
    "l": 1225.85,
    "c": 1228.65,
    "v": 290576
  },
  {
    "t": "2024-12-24T09:30:00+05:30",
    "o": 1226.35,
    "h": 1228,
    "l": 1223,
    "c": 1227.9,
    "v": 309365
  },
  {
    "t": "2024-12-24T09:15:00+05:30",
    "o": 1222.3,
    "h": 1227.5,
    "l": 1221.35,
    "c": 1226,
    "v": 607541
  },
  {
    "t": "2024-12-23T15:15:00+05:30",
    "o": 1222.9,
    "h": 1223.9,
    "l": 1221.8,
    "c": 1223.85,
    "v": 812662
  },
  {
    "t": "2024-12-23T15:00:00+05:30",
    "o": 1221.25,
    "h": 1223,
    "l": 1220.5,
    "c": 1222.95,
    "v": 643196
  },
  {
    "t": "2024-12-23T14:45:00+05:30",
    "o": 1221.45,
    "h": 1222.3,
    "l": 1220.4,
    "c": 1221.5,
    "v": 186190
  },
  {
    "t": "2024-12-23T14:30:00+05:30",
    "o": 1221.3,
    "h": 1224.5,
    "l": 1220.9,
    "c": 1221.75,
    "v": 290193
  },
  {
    "t": "2024-12-23T14:15:00+05:30",
    "o": 1218.85,
    "h": 1222,
    "l": 1218.1,
    "c": 1221.35,
    "v": 308234
  },
  {
    "t": "2024-12-23T14:00:00+05:30",
    "o": 1215.4,
    "h": 1219,
    "l": 1213.8,
    "c": 1218.7,
    "v": 222134
  },
  {
    "t": "2024-12-23T13:45:00+05:30",
    "o": 1217.85,
    "h": 1218.7,
    "l": 1214.6,
    "c": 1215.5,
    "v": 187027
  },
  {
    "t": "2024-12-23T13:30:00+05:30",
    "o": 1214.7,
    "h": 1218.05,
    "l": 1213.2,
    "c": 1217.9,
    "v": 309786
  },
  {
    "t": "2024-12-23T13:15:00+05:30",
    "o": 1215,
    "h": 1216.5,
    "l": 1214.2,
    "c": 1214.95,
    "v": 231347
  },
  {
    "t": "2024-12-23T13:00:00+05:30",
    "o": 1215.25,
    "h": 1218,
    "l": 1214.25,
    "c": 1215,
    "v": 252531
  },
  {
    "t": "2024-12-23T12:45:00+05:30",
    "o": 1218.8,
    "h": 1219.6,
    "l": 1214.5,
    "c": 1215.3,
    "v": 343773
  },
  {
    "t": "2024-12-23T12:30:00+05:30",
    "o": 1218.1,
    "h": 1219.1,
    "l": 1215.2,
    "c": 1218.75,
    "v": 380654
  },
  {
    "t": "2024-12-23T12:15:00+05:30",
    "o": 1220,
    "h": 1220.8,
    "l": 1217.7,
    "c": 1218.1,
    "v": 316996
  },
  {
    "t": "2024-12-23T12:00:00+05:30",
    "o": 1223.15,
    "h": 1224.5,
    "l": 1218.75,
    "c": 1220.05,
    "v": 387293
  },
  {
    "t": "2024-12-23T11:45:00+05:30",
    "o": 1225.9,
    "h": 1226.9,
    "l": 1222.45,
    "c": 1223.15,
    "v": 239005
  },
  {
    "t": "2024-12-23T11:30:00+05:30",
    "o": 1225.65,
    "h": 1227.2,
    "l": 1224.7,
    "c": 1225.9,
    "v": 273912
  },
  {
    "t": "2024-12-23T11:15:00+05:30",
    "o": 1223.7,
    "h": 1226.35,
    "l": 1223.7,
    "c": 1225.85,
    "v": 374400
  },
  {
    "t": "2024-12-23T11:00:00+05:30",
    "o": 1222.15,
    "h": 1224.5,
    "l": 1221.95,
    "c": 1223.85,
    "v": 315386
  },
  {
    "t": "2024-12-23T10:45:00+05:30",
    "o": 1219.2,
    "h": 1223,
    "l": 1218.6,
    "c": 1222.3,
    "v": 339876
  },
  {
    "t": "2024-12-23T10:30:00+05:30",
    "o": 1219,
    "h": 1221.4,
    "l": 1218.6,
    "c": 1219.3,
    "v": 426284
  },
  {
    "t": "2024-12-23T10:15:00+05:30",
    "o": 1218.2,
    "h": 1219.85,
    "l": 1216.2,
    "c": 1219.15,
    "v": 561387
  },
  {
    "t": "2024-12-23T10:00:00+05:30",
    "o": 1215.65,
    "h": 1219.85,
    "l": 1214,
    "c": 1218.2,
    "v": 318243
  },
  {
    "t": "2024-12-23T09:45:00+05:30",
    "o": 1219.55,
    "h": 1221,
    "l": 1214.45,
    "c": 1215.8,
    "v": 288635
  },
  {
    "t": "2024-12-23T09:30:00+05:30",
    "o": 1217.5,
    "h": 1220.65,
    "l": 1214,
    "c": 1219.55,
    "v": 402264
  },
  {
    "t": "2024-12-23T09:15:00+05:30",
    "o": 1215,
    "h": 1223.2,
    "l": 1213.6,
    "c": 1217.5,
    "v": 1545811
  },
  {
    "t": "2024-12-20T15:15:00+05:30",
    "o": 1203.05,
    "h": 1207,
    "l": 1201.5,
    "c": 1206,
    "v": 3934638
  },
  {
    "t": "2024-12-20T15:00:00+05:30",
    "o": 1212.05,
    "h": 1212.1,
    "l": 1202.3,
    "c": 1203.05,
    "v": 4615057
  },
  {
    "t": "2024-12-20T14:45:00+05:30",
    "o": 1214.25,
    "h": 1214.4,
    "l": 1212,
    "c": 1212.15,
    "v": 608990
  },
  {
    "t": "2024-12-20T14:30:00+05:30",
    "o": 1216,
    "h": 1216.2,
    "l": 1212.5,
    "c": 1214.25,
    "v": 580525
  },
  {
    "t": "2024-12-20T14:15:00+05:30",
    "o": 1211.15,
    "h": 1216.7,
    "l": 1210.1,
    "c": 1216,
    "v": 481051
  },
  {
    "t": "2024-12-20T14:00:00+05:30",
    "o": 1216.1,
    "h": 1216.1,
    "l": 1209.6,
    "c": 1211.15,
    "v": 1082839
  },
  {
    "t": "2024-12-20T13:45:00+05:30",
    "o": 1217.35,
    "h": 1217.75,
    "l": 1214.95,
    "c": 1216.1,
    "v": 570211
  },
  {
    "t": "2024-12-20T13:30:00+05:30",
    "o": 1220,
    "h": 1221,
    "l": 1216.8,
    "c": 1217.35,
    "v": 539837
  },
  {
    "t": "2024-12-20T13:15:00+05:30",
    "o": 1219.8,
    "h": 1220.65,
    "l": 1217.6,
    "c": 1220.1,
    "v": 598767
  },
  {
    "t": "2024-12-20T13:00:00+05:30",
    "o": 1221.2,
    "h": 1222,
    "l": 1218.55,
    "c": 1219.8,
    "v": 580219
  },
  {
    "t": "2024-12-20T12:45:00+05:30",
    "o": 1225,
    "h": 1225.75,
    "l": 1220.5,
    "c": 1221.45,
    "v": 558491
  },
  {
    "t": "2024-12-20T12:30:00+05:30",
    "o": 1228,
    "h": 1228.75,
    "l": 1224.5,
    "c": 1225,
    "v": 470090
  },
  {
    "t": "2024-12-20T12:15:00+05:30",
    "o": 1230,
    "h": 1230,
    "l": 1226.7,
    "c": 1228,
    "v": 440609
  },
  {
    "t": "2024-12-20T12:00:00+05:30",
    "o": 1234.6,
    "h": 1235.3,
    "l": 1229.45,
    "c": 1230,
    "v": 355825
  },
  {
    "t": "2024-12-20T11:45:00+05:30",
    "o": 1233.4,
    "h": 1235,
    "l": 1233,
    "c": 1234.55,
    "v": 173693
  },
  {
    "t": "2024-12-20T11:30:00+05:30",
    "o": 1233,
    "h": 1234,
    "l": 1232.05,
    "c": 1233.4,
    "v": 221908
  },
  {
    "t": "2024-12-20T11:15:00+05:30",
    "o": 1234.05,
    "h": 1235,
    "l": 1231.05,
    "c": 1233,
    "v": 391564
  },
  {
    "t": "2024-12-20T11:00:00+05:30",
    "o": 1234.1,
    "h": 1235.3,
    "l": 1233,
    "c": 1234,
    "v": 148223
  },
  {
    "t": "2024-12-20T10:45:00+05:30",
    "o": 1232.8,
    "h": 1237,
    "l": 1232.2,
    "c": 1234.4,
    "v": 289485
  },
  {
    "t": "2024-12-20T10:30:00+05:30",
    "o": 1228.4,
    "h": 1234.9,
    "l": 1228.4,
    "c": 1233.15,
    "v": 442052
  },
  {
    "t": "2024-12-20T10:15:00+05:30",
    "o": 1224.7,
    "h": 1230,
    "l": 1223.1,
    "c": 1228.4,
    "v": 400111
  },
  {
    "t": "2024-12-20T10:00:00+05:30",
    "o": 1226.1,
    "h": 1228,
    "l": 1222.3,
    "c": 1224.7,
    "v": 480845
  },
  {
    "t": "2024-12-20T09:45:00+05:30",
    "o": 1237.5,
    "h": 1237.6,
    "l": 1225.05,
    "c": 1226.15,
    "v": 763191
  },
  {
    "t": "2024-12-20T09:30:00+05:30",
    "o": 1230.35,
    "h": 1239.5,
    "l": 1230.1,
    "c": 1237.5,
    "v": 541255
  },
  {
    "t": "2024-12-20T09:15:00+05:30",
    "o": 1224,
    "h": 1232.85,
    "l": 1223.25,
    "c": 1230.4,
    "v": 890044
  },
  {
    "t": "2024-12-19T15:15:00+05:30",
    "o": 1230.25,
    "h": 1230.55,
    "l": 1229,
    "c": 1230.2,
    "v": 1249055
  },
  {
    "t": "2024-12-19T15:00:00+05:30",
    "o": 1230.95,
    "h": 1232.7,
    "l": 1229.95,
    "c": 1230.2,
    "v": 1125072
  },
  {
    "t": "2024-12-19T14:45:00+05:30",
    "o": 1231.55,
    "h": 1233.55,
    "l": 1230.4,
    "c": 1230.9,
    "v": 545485
  },
  {
    "t": "2024-12-19T14:30:00+05:30",
    "o": 1231.35,
    "h": 1233,
    "l": 1231,
    "c": 1231.5,
    "v": 529325
  },
  {
    "t": "2024-12-19T14:15:00+05:30",
    "o": 1231.75,
    "h": 1231.85,
    "l": 1229.5,
    "c": 1231.25,
    "v": 661311
  },
  {
    "t": "2024-12-19T14:00:00+05:30",
    "o": 1231.65,
    "h": 1233.15,
    "l": 1231.3,
    "c": 1231.35,
    "v": 337590
  },
  {
    "t": "2024-12-19T13:45:00+05:30",
    "o": 1231.55,
    "h": 1232.45,
    "l": 1230.1,
    "c": 1231.6,
    "v": 371658
  },
  {
    "t": "2024-12-19T13:30:00+05:30",
    "o": 1231.8,
    "h": 1232.35,
    "l": 1230.85,
    "c": 1231.55,
    "v": 310497
  },
  {
    "t": "2024-12-19T13:15:00+05:30",
    "o": 1234.15,
    "h": 1234.2,
    "l": 1231,
    "c": 1231.6,
    "v": 410175
  },
  {
    "t": "2024-12-19T13:00:00+05:30",
    "o": 1233.75,
    "h": 1235,
    "l": 1233.2,
    "c": 1234.15,
    "v": 443180
  },
  {
    "t": "2024-12-19T12:45:00+05:30",
    "o": 1235.75,
    "h": 1236,
    "l": 1233.05,
    "c": 1233.95,
    "v": 747377
  },
  {
    "t": "2024-12-19T12:30:00+05:30",
    "o": 1238.1,
    "h": 1238.35,
    "l": 1235.5,
    "c": 1235.75,
    "v": 319269
  },
  {
    "t": "2024-12-19T12:15:00+05:30",
    "o": 1238.65,
    "h": 1240,
    "l": 1237.35,
    "c": 1238.1,
    "v": 392583
  },
  {
    "t": "2024-12-19T12:00:00+05:30",
    "o": 1237.7,
    "h": 1239.05,
    "l": 1236.2,
    "c": 1238.8,
    "v": 420380
  },
  {
    "t": "2024-12-19T11:45:00+05:30",
    "o": 1237.45,
    "h": 1238.1,
    "l": 1235.8,
    "c": 1237.75,
    "v": 399262
  },
  {
    "t": "2024-12-19T11:30:00+05:30",
    "o": 1238.15,
    "h": 1238.35,
    "l": 1235.5,
    "c": 1237.45,
    "v": 378796
  },
  {
    "t": "2024-12-19T11:15:00+05:30",
    "o": 1237.7,
    "h": 1239.5,
    "l": 1237.15,
    "c": 1238.15,
    "v": 274211
  },
  {
    "t": "2024-12-19T11:00:00+05:30",
    "o": 1238.5,
    "h": 1238.95,
    "l": 1236.2,
    "c": 1237.7,
    "v": 395036
  },
  {
    "t": "2024-12-19T10:45:00+05:30",
    "o": 1241.2,
    "h": 1241.55,
    "l": 1238,
    "c": 1238.5,
    "v": 184326
  },
  {
    "t": "2024-12-19T10:30:00+05:30",
    "o": 1239.5,
    "h": 1241.85,
    "l": 1238.9,
    "c": 1241.35,
    "v": 219556
  },
  {
    "t": "2024-12-19T10:15:00+05:30",
    "o": 1240.25,
    "h": 1241.8,
    "l": 1238.5,
    "c": 1239.5,
    "v": 305439
  },
  {
    "t": "2024-12-19T10:00:00+05:30",
    "o": 1240.85,
    "h": 1244.9,
    "l": 1238.25,
    "c": 1240,
    "v": 1495705
  },
  {
    "t": "2024-12-19T09:45:00+05:30",
    "o": 1241.05,
    "h": 1243.2,
    "l": 1239,
    "c": 1240.5,
    "v": 510237
  },
  {
    "t": "2024-12-19T09:30:00+05:30",
    "o": 1235.9,
    "h": 1242.9,
    "l": 1234.4,
    "c": 1241.05,
    "v": 515303
  },
  {
    "t": "2024-12-19T09:15:00+05:30",
    "o": 1239,
    "h": 1244.4,
    "l": 1234.35,
    "c": 1235.9,
    "v": 1617698
  },
  {
    "t": "2024-12-18T15:15:00+05:30",
    "o": 1253.35,
    "h": 1254.85,
    "l": 1252,
    "c": 1254.35,
    "v": 1041353
  },
  {
    "t": "2024-12-18T15:00:00+05:30",
    "o": 1254.45,
    "h": 1254.5,
    "l": 1252,
    "c": 1253.4,
    "v": 944780
  },
  {
    "t": "2024-12-18T14:45:00+05:30",
    "o": 1255,
    "h": 1255.6,
    "l": 1253.6,
    "c": 1254.1,
    "v": 405879
  },
  {
    "t": "2024-12-18T14:30:00+05:30",
    "o": 1254.8,
    "h": 1255.9,
    "l": 1254,
    "c": 1255,
    "v": 431329
  },
  {
    "t": "2024-12-18T14:15:00+05:30",
    "o": 1254.4,
    "h": 1257.8,
    "l": 1253.8,
    "c": 1254.8,
    "v": 417994
  },
  {
    "t": "2024-12-18T14:00:00+05:30",
    "o": 1253.65,
    "h": 1254.9,
    "l": 1252.9,
    "c": 1254.45,
    "v": 283056
  },
  {
    "t": "2024-12-18T13:45:00+05:30",
    "o": 1251.55,
    "h": 1254.3,
    "l": 1251.25,
    "c": 1253.7,
    "v": 426761
  },
  {
    "t": "2024-12-18T13:30:00+05:30",
    "o": 1252.7,
    "h": 1253.5,
    "l": 1251.3,
    "c": 1251.85,
    "v": 335414
  },
  {
    "t": "2024-12-18T13:15:00+05:30",
    "o": 1252.05,
    "h": 1254.35,
    "l": 1251.75,
    "c": 1252.7,
    "v": 381187
  },
  {
    "t": "2024-12-18T13:00:00+05:30",
    "o": 1249.55,
    "h": 1253,
    "l": 1248.9,
    "c": 1252.05,
    "v": 385859
  },
  {
    "t": "2024-12-18T12:45:00+05:30",
    "o": 1246.8,
    "h": 1249.6,
    "l": 1245.55,
    "c": 1249.3,
    "v": 357015
  },
  {
    "t": "2024-12-18T12:30:00+05:30",
    "o": 1249.05,
    "h": 1249.5,
    "l": 1245.85,
    "c": 1246.8,
    "v": 450522
  },
  {
    "t": "2024-12-18T12:15:00+05:30",
    "o": 1252.05,
    "h": 1252.75,
    "l": 1247.25,
    "c": 1249.05,
    "v": 504657
  },
  {
    "t": "2024-12-18T12:00:00+05:30",
    "o": 1253.1,
    "h": 1254.15,
    "l": 1251.2,
    "c": 1252.05,
    "v": 311660
  },
  {
    "t": "2024-12-18T11:45:00+05:30",
    "o": 1254.9,
    "h": 1255.75,
    "l": 1253.1,
    "c": 1253.1,
    "v": 234442
  },
  {
    "t": "2024-12-18T11:30:00+05:30",
    "o": 1254.9,
    "h": 1256.5,
    "l": 1254,
    "c": 1254.95,
    "v": 254523
  },
  {
    "t": "2024-12-18T11:15:00+05:30",
    "o": 1253.45,
    "h": 1255.85,
    "l": 1251.9,
    "c": 1254.95,
    "v": 279492
  },
  {
    "t": "2024-12-18T11:00:00+05:30",
    "o": 1254.45,
    "h": 1255.9,
    "l": 1253.1,
    "c": 1253.45,
    "v": 278603
  },
  {
    "t": "2024-12-18T10:45:00+05:30",
    "o": 1258.9,
    "h": 1259.95,
    "l": 1253.2,
    "c": 1254.35,
    "v": 564872
  },
  {
    "t": "2024-12-18T10:30:00+05:30",
    "o": 1254.5,
    "h": 1259.85,
    "l": 1254.25,
    "c": 1258.85,
    "v": 452393
  },
  {
    "t": "2024-12-18T10:15:00+05:30",
    "o": 1253.25,
    "h": 1255.95,
    "l": 1251.8,
    "c": 1254.5,
    "v": 441657
  },
  {
    "t": "2024-12-18T10:00:00+05:30",
    "o": 1251.6,
    "h": 1253.75,
    "l": 1250,
    "c": 1253.25,
    "v": 463718
  },
  {
    "t": "2024-12-18T09:45:00+05:30",
    "o": 1257.9,
    "h": 1258.5,
    "l": 1251,
    "c": 1251.6,
    "v": 733640
  },
  {
    "t": "2024-12-18T09:30:00+05:30",
    "o": 1252.3,
    "h": 1258.3,
    "l": 1251.5,
    "c": 1257.9,
    "v": 967569
  },
  {
    "t": "2024-12-18T09:15:00+05:30",
    "o": 1240.65,
    "h": 1252.55,
    "l": 1240.65,
    "c": 1252.3,
    "v": 1185899
  },
  {
    "t": "2024-12-17T15:15:00+05:30",
    "o": 1245.9,
    "h": 1246.05,
    "l": 1243.95,
    "c": 1244.7,
    "v": 1146783
  },
  {
    "t": "2024-12-17T15:00:00+05:30",
    "o": 1243.95,
    "h": 1247,
    "l": 1243.45,
    "c": 1245.95,
    "v": 1365175
  },
  {
    "t": "2024-12-17T14:45:00+05:30",
    "o": 1245.65,
    "h": 1246,
    "l": 1242.8,
    "c": 1244,
    "v": 726341
  },
  {
    "t": "2024-12-17T14:30:00+05:30",
    "o": 1244.7,
    "h": 1246.25,
    "l": 1243.4,
    "c": 1245.65,
    "v": 595641
  },
  {
    "t": "2024-12-17T14:15:00+05:30",
    "o": 1245.35,
    "h": 1246.3,
    "l": 1244,
    "c": 1244.7,
    "v": 607170
  },
  {
    "t": "2024-12-17T14:00:00+05:30",
    "o": 1246.7,
    "h": 1247.25,
    "l": 1245.05,
    "c": 1245.35,
    "v": 497868
  },
  {
    "t": "2024-12-17T13:45:00+05:30",
    "o": 1246.85,
    "h": 1247.95,
    "l": 1245.05,
    "c": 1246.7,
    "v": 466186
  },
  {
    "t": "2024-12-17T13:30:00+05:30",
    "o": 1246.5,
    "h": 1248,
    "l": 1245.6,
    "c": 1246.85,
    "v": 395791
  },
  {
    "t": "2024-12-17T13:15:00+05:30",
    "o": 1248.1,
    "h": 1249.3,
    "l": 1246.35,
    "c": 1246.7,
    "v": 427832
  },
  {
    "t": "2024-12-17T13:00:00+05:30",
    "o": 1249.95,
    "h": 1250.4,
    "l": 1247,
    "c": 1248.1,
    "v": 468901
  },
  {
    "t": "2024-12-17T12:45:00+05:30",
    "o": 1248.1,
    "h": 1250.1,
    "l": 1246.5,
    "c": 1249.95,
    "v": 406436
  },
  {
    "t": "2024-12-17T12:30:00+05:30",
    "o": 1249.1,
    "h": 1251.9,
    "l": 1247.85,
    "c": 1248.15,
    "v": 454413
  },
  {
    "t": "2024-12-17T12:15:00+05:30",
    "o": 1248.95,
    "h": 1249.5,
    "l": 1247,
    "c": 1249.3,
    "v": 576071
  },
  {
    "t": "2024-12-17T12:00:00+05:30",
    "o": 1249.35,
    "h": 1250,
    "l": 1248.45,
    "c": 1248.6,
    "v": 427867
  },
  {
    "t": "2024-12-17T11:45:00+05:30",
    "o": 1249.3,
    "h": 1250.4,
    "l": 1248.95,
    "c": 1249.35,
    "v": 396301
  },
  {
    "t": "2024-12-17T11:30:00+05:30",
    "o": 1250.65,
    "h": 1250.95,
    "l": 1248.55,
    "c": 1249.3,
    "v": 545652
  },
  {
    "t": "2024-12-17T11:15:00+05:30",
    "o": 1251.05,
    "h": 1253,
    "l": 1250.05,
    "c": 1250.25,
    "v": 356383
  },
  {
    "t": "2024-12-17T11:00:00+05:30",
    "o": 1253.4,
    "h": 1253.8,
    "l": 1250.55,
    "c": 1251,
    "v": 295434
  },
  {
    "t": "2024-12-17T10:45:00+05:30",
    "o": 1251,
    "h": 1253.9,
    "l": 1250.65,
    "c": 1253.4,
    "v": 630207
  },
  {
    "t": "2024-12-17T10:30:00+05:30",
    "o": 1250.85,
    "h": 1251,
    "l": 1248,
    "c": 1251,
    "v": 2788775
  },
  {
    "t": "2024-12-17T10:15:00+05:30",
    "o": 1253.4,
    "h": 1254,
    "l": 1249,
    "c": 1250.85,
    "v": 733166
  },
  {
    "t": "2024-12-17T10:00:00+05:30",
    "o": 1252.8,
    "h": 1253.9,
    "l": 1251.5,
    "c": 1253.4,
    "v": 397561
  },
  {
    "t": "2024-12-17T09:45:00+05:30",
    "o": 1254.45,
    "h": 1254.5,
    "l": 1251.35,
    "c": 1252.85,
    "v": 770468
  },
  {
    "t": "2024-12-17T09:30:00+05:30",
    "o": 1257.2,
    "h": 1257.5,
    "l": 1254,
    "c": 1254.45,
    "v": 549956
  },
  {
    "t": "2024-12-17T09:15:00+05:30",
    "o": 1261.05,
    "h": 1263.9,
    "l": 1253.45,
    "c": 1257.2,
    "v": 1244686
  },
  {
    "t": "2024-12-16T15:15:00+05:30",
    "o": 1268.75,
    "h": 1268.95,
    "l": 1266.8,
    "c": 1268.4,
    "v": 654937
  },
  {
    "t": "2024-12-16T15:00:00+05:30",
    "o": 1269.1,
    "h": 1269.95,
    "l": 1267.3,
    "c": 1268.75,
    "v": 661101
  },
  {
    "t": "2024-12-16T14:45:00+05:30",
    "o": 1268.5,
    "h": 1270,
    "l": 1267.55,
    "c": 1269.1,
    "v": 353530
  },
  {
    "t": "2024-12-16T14:30:00+05:30",
    "o": 1267.5,
    "h": 1269.7,
    "l": 1266.9,
    "c": 1268.5,
    "v": 265975
  },
  {
    "t": "2024-12-16T14:15:00+05:30",
    "o": 1268.95,
    "h": 1269,
    "l": 1266.55,
    "c": 1267.45,
    "v": 208481
  },
  {
    "t": "2024-12-16T14:00:00+05:30",
    "o": 1268.8,
    "h": 1269.95,
    "l": 1268.25,
    "c": 1268.9,
    "v": 188476
  },
  {
    "t": "2024-12-16T13:45:00+05:30",
    "o": 1269.75,
    "h": 1269.95,
    "l": 1268,
    "c": 1268.8,
    "v": 223553
  },
  {
    "t": "2024-12-16T13:30:00+05:30",
    "o": 1270.05,
    "h": 1270.25,
    "l": 1267.5,
    "c": 1269.65,
    "v": 279255
  },
  {
    "t": "2024-12-16T13:15:00+05:30",
    "o": 1271.45,
    "h": 1271.5,
    "l": 1269.9,
    "c": 1269.9,
    "v": 625455
  },
  {
    "t": "2024-12-16T13:00:00+05:30",
    "o": 1271.95,
    "h": 1272.65,
    "l": 1270.5,
    "c": 1271.45,
    "v": 355328
  },
  {
    "t": "2024-12-16T12:45:00+05:30",
    "o": 1271.5,
    "h": 1272,
    "l": 1270.4,
    "c": 1271.9,
    "v": 128657
  },
  {
    "t": "2024-12-16T12:30:00+05:30",
    "o": 1271,
    "h": 1271.95,
    "l": 1269.5,
    "c": 1271.5,
    "v": 341896
  },
  {
    "t": "2024-12-16T12:15:00+05:30",
    "o": 1270.05,
    "h": 1272.45,
    "l": 1269.2,
    "c": 1271.05,
    "v": 477927
  },
  {
    "t": "2024-12-16T12:00:00+05:30",
    "o": 1271.25,
    "h": 1271.5,
    "l": 1270,
    "c": 1270,
    "v": 266405
  },
  {
    "t": "2024-12-16T11:45:00+05:30",
    "o": 1270.05,
    "h": 1273.3,
    "l": 1270,
    "c": 1271.1,
    "v": 386290
  },
  {
    "t": "2024-12-16T11:30:00+05:30",
    "o": 1271.2,
    "h": 1272.4,
    "l": 1270,
    "c": 1270.3,
    "v": 305592
  },
  {
    "t": "2024-12-16T11:15:00+05:30",
    "o": 1270.5,
    "h": 1272.25,
    "l": 1268.65,
    "c": 1271.2,
    "v": 423179
  },
  {
    "t": "2024-12-16T11:00:00+05:30",
    "o": 1271.4,
    "h": 1272.75,
    "l": 1269.6,
    "c": 1270.55,
    "v": 393055
  },
  {
    "t": "2024-12-16T10:45:00+05:30",
    "o": 1273.1,
    "h": 1275.35,
    "l": 1271.05,
    "c": 1271.3,
    "v": 294319
  },
  {
    "t": "2024-12-16T10:30:00+05:30",
    "o": 1272,
    "h": 1273.95,
    "l": 1271.3,
    "c": 1273.1,
    "v": 302491
  },
  {
    "t": "2024-12-16T10:15:00+05:30",
    "o": 1276.25,
    "h": 1276.25,
    "l": 1271.5,
    "c": 1272,
    "v": 313743
  },
  {
    "t": "2024-12-16T10:00:00+05:30",
    "o": 1276.6,
    "h": 1277,
    "l": 1275,
    "c": 1276.25,
    "v": 229730
  },
  {
    "t": "2024-12-16T09:45:00+05:30",
    "o": 1277.9,
    "h": 1278.9,
    "l": 1276.3,
    "c": 1276.3,
    "v": 322140
  },
  {
    "t": "2024-12-16T09:30:00+05:30",
    "o": 1278.5,
    "h": 1280,
    "l": 1276.1,
    "c": 1277.9,
    "v": 464238
  },
  {
    "t": "2024-12-16T09:15:00+05:30",
    "o": 1275,
    "h": 1281,
    "l": 1275,
    "c": 1278.55,
    "v": 953191
  },
  {
    "t": "2024-12-13T15:15:00+05:30",
    "o": 1272.75,
    "h": 1275.2,
    "l": 1271.75,
    "c": 1274.45,
    "v": 1332552
  },
  {
    "t": "2024-12-13T15:00:00+05:30",
    "o": 1269.9,
    "h": 1275,
    "l": 1268.75,
    "c": 1272.75,
    "v": 1608519
  },
  {
    "t": "2024-12-13T14:45:00+05:30",
    "o": 1270.85,
    "h": 1271.6,
    "l": 1269.3,
    "c": 1269.9,
    "v": 1248229
  },
  {
    "t": "2024-12-13T14:30:00+05:30",
    "o": 1273,
    "h": 1274,
    "l": 1270.15,
    "c": 1270.9,
    "v": 1003370
  },
  {
    "t": "2024-12-13T14:15:00+05:30",
    "o": 1272.5,
    "h": 1273.9,
    "l": 1271,
    "c": 1273.2,
    "v": 570277
  },
  {
    "t": "2024-12-13T14:00:00+05:30",
    "o": 1270.6,
    "h": 1274,
    "l": 1270.55,
    "c": 1272.55,
    "v": 876236
  },
  {
    "t": "2024-12-13T13:45:00+05:30",
    "o": 1270.95,
    "h": 1273.95,
    "l": 1268.45,
    "c": 1270.6,
    "v": 1289815
  },
  {
    "t": "2024-12-13T13:30:00+05:30",
    "o": 1267.25,
    "h": 1272.6,
    "l": 1266,
    "c": 1270.85,
    "v": 1246726
  },
  {
    "t": "2024-12-13T13:15:00+05:30",
    "o": 1261.8,
    "h": 1267.4,
    "l": 1259.45,
    "c": 1267.4,
    "v": 845554
  },
  {
    "t": "2024-12-13T13:00:00+05:30",
    "o": 1262.65,
    "h": 1267,
    "l": 1260.4,
    "c": 1261.95,
    "v": 1034539
  },
  {
    "t": "2024-12-13T12:45:00+05:30",
    "o": 1255.6,
    "h": 1263.85,
    "l": 1254.1,
    "c": 1262.7,
    "v": 536949
  },
  {
    "t": "2024-12-13T12:30:00+05:30",
    "o": 1259.5,
    "h": 1259.6,
    "l": 1254,
    "c": 1255.65,
    "v": 460404
  },
  {
    "t": "2024-12-13T12:15:00+05:30",
    "o": 1255.55,
    "h": 1263.05,
    "l": 1255.1,
    "c": 1259.6,
    "v": 1089965
  },
  {
    "t": "2024-12-13T12:00:00+05:30",
    "o": 1252.7,
    "h": 1256.45,
    "l": 1249.35,
    "c": 1255.1,
    "v": 2240895
  },
  {
    "t": "2024-12-13T11:45:00+05:30",
    "o": 1247.4,
    "h": 1253.2,
    "l": 1246.5,
    "c": 1252.9,
    "v": 1209832
  },
  {
    "t": "2024-12-13T11:30:00+05:30",
    "o": 1246.45,
    "h": 1249.4,
    "l": 1245,
    "c": 1247.45,
    "v": 1695863
  },
  {
    "t": "2024-12-13T11:15:00+05:30",
    "o": 1245.95,
    "h": 1249.55,
    "l": 1245,
    "c": 1246.6,
    "v": 827931
  },
  {
    "t": "2024-12-13T11:00:00+05:30",
    "o": 1245.65,
    "h": 1248.65,
    "l": 1244,
    "c": 1246.05,
    "v": 761077
  },
  {
    "t": "2024-12-13T10:45:00+05:30",
    "o": 1242.15,
    "h": 1247.65,
    "l": 1239.7,
    "c": 1245.65,
    "v": 684598
  },
  {
    "t": "2024-12-13T10:30:00+05:30",
    "o": 1243.1,
    "h": 1243.35,
    "l": 1239.6,
    "c": 1242.2,
    "v": 903910
  },
  {
    "t": "2024-12-13T10:15:00+05:30",
    "o": 1246.05,
    "h": 1246.15,
    "l": 1240.2,
    "c": 1243.15,
    "v": 3173825
  },
  {
    "t": "2024-12-13T10:00:00+05:30",
    "o": 1247.7,
    "h": 1248,
    "l": 1245.45,
    "c": 1246.15,
    "v": 425437
  },
  {
    "t": "2024-12-13T09:45:00+05:30",
    "o": 1252.4,
    "h": 1252.5,
    "l": 1247,
    "c": 1247.75,
    "v": 882993
  },
  {
    "t": "2024-12-13T09:30:00+05:30",
    "o": 1254.3,
    "h": 1255.65,
    "l": 1251,
    "c": 1252.35,
    "v": 875568
  },
  {
    "t": "2024-12-13T09:15:00+05:30",
    "o": 1260,
    "h": 1264.9,
    "l": 1253,
    "c": 1254.25,
    "v": 1602988
  },
  {
    "t": "2024-12-12T15:15:00+05:30",
    "o": 1263.85,
    "h": 1264,
    "l": 1260.6,
    "c": 1261.3,
    "v": 1555701
  },
  {
    "t": "2024-12-12T15:00:00+05:30",
    "o": 1262.95,
    "h": 1264.7,
    "l": 1261.75,
    "c": 1263.75,
    "v": 2453749
  },
  {
    "t": "2024-12-12T14:45:00+05:30",
    "o": 1263.05,
    "h": 1263.7,
    "l": 1260.85,
    "c": 1262.95,
    "v": 1162914
  },
  {
    "t": "2024-12-12T14:30:00+05:30",
    "o": 1264.6,
    "h": 1264.9,
    "l": 1262.4,
    "c": 1263,
    "v": 414332
  },
  {
    "t": "2024-12-12T14:15:00+05:30",
    "o": 1265.85,
    "h": 1266.8,
    "l": 1263.1,
    "c": 1264.6,
    "v": 493370
  },
  {
    "t": "2024-12-12T14:00:00+05:30",
    "o": 1264.65,
    "h": 1266.8,
    "l": 1264.35,
    "c": 1265.85,
    "v": 401541
  },
  {
    "t": "2024-12-12T13:45:00+05:30",
    "o": 1265.4,
    "h": 1268.1,
    "l": 1264,
    "c": 1264.65,
    "v": 528924
  },
  {
    "t": "2024-12-12T13:30:00+05:30",
    "o": 1262.4,
    "h": 1265.9,
    "l": 1261.25,
    "c": 1265.6,
    "v": 1827063
  },
  {
    "t": "2024-12-12T13:15:00+05:30",
    "o": 1265.25,
    "h": 1269.45,
    "l": 1262.2,
    "c": 1262.4,
    "v": 545208
  },
  {
    "t": "2024-12-12T13:00:00+05:30",
    "o": 1263.55,
    "h": 1270,
    "l": 1261.3,
    "c": 1265.7,
    "v": 3720038
  },
  {
    "t": "2024-12-12T12:45:00+05:30",
    "o": 1264.6,
    "h": 1265.65,
    "l": 1263.1,
    "c": 1263.55,
    "v": 319336
  },
  {
    "t": "2024-12-12T12:30:00+05:30",
    "o": 1262.5,
    "h": 1266,
    "l": 1262.5,
    "c": 1264.7,
    "v": 398777
  },
  {
    "t": "2024-12-12T12:15:00+05:30",
    "o": 1263,
    "h": 1264.4,
    "l": 1261.1,
    "c": 1262.8,
    "v": 327262
  },
  {
    "t": "2024-12-12T12:00:00+05:30",
    "o": 1267.4,
    "h": 1267.45,
    "l": 1262.55,
    "c": 1263,
    "v": 512511
  },
  {
    "t": "2024-12-12T11:45:00+05:30",
    "o": 1268.85,
    "h": 1269,
    "l": 1266.6,
    "c": 1267.45,
    "v": 347488
  },
  {
    "t": "2024-12-12T11:30:00+05:30",
    "o": 1268.15,
    "h": 1269.4,
    "l": 1267.5,
    "c": 1268.85,
    "v": 390024
  },
  {
    "t": "2024-12-12T11:15:00+05:30",
    "o": 1269.25,
    "h": 1270,
    "l": 1268,
    "c": 1268.15,
    "v": 390286
  },
  {
    "t": "2024-12-12T11:00:00+05:30",
    "o": 1268.4,
    "h": 1269.75,
    "l": 1266.55,
    "c": 1269.25,
    "v": 674318
  },
  {
    "t": "2024-12-12T10:45:00+05:30",
    "o": 1268.5,
    "h": 1270.55,
    "l": 1268.1,
    "c": 1268.15,
    "v": 493236
  },
  {
    "t": "2024-12-12T10:30:00+05:30",
    "o": 1270.6,
    "h": 1271.4,
    "l": 1268.2,
    "c": 1268.55,
    "v": 545965
  },
  {
    "t": "2024-12-12T10:15:00+05:30",
    "o": 1271.05,
    "h": 1273,
    "l": 1270,
    "c": 1270.65,
    "v": 473522
  },
  {
    "t": "2024-12-12T10:00:00+05:30",
    "o": 1274.15,
    "h": 1274.35,
    "l": 1271,
    "c": 1271.05,
    "v": 433404
  },
  {
    "t": "2024-12-12T09:45:00+05:30",
    "o": 1274.35,
    "h": 1275,
    "l": 1272.5,
    "c": 1274.4,
    "v": 350154
  },
  {
    "t": "2024-12-12T09:30:00+05:30",
    "o": 1277.5,
    "h": 1278.2,
    "l": 1273.5,
    "c": 1274.3,
    "v": 395306
  },
  {
    "t": "2024-12-12T09:15:00+05:30",
    "o": 1270,
    "h": 1277.55,
    "l": 1270,
    "c": 1277.3,
    "v": 1429623
  },
  {
    "t": "2024-12-11T15:15:00+05:30",
    "o": 1278.25,
    "h": 1279.25,
    "l": 1276.9,
    "c": 1279,
    "v": 1296596
  },
  {
    "t": "2024-12-11T15:00:00+05:30",
    "o": 1278.15,
    "h": 1279.3,
    "l": 1277.6,
    "c": 1278.25,
    "v": 1139067
  },
  {
    "t": "2024-12-11T14:45:00+05:30",
    "o": 1277.4,
    "h": 1278.5,
    "l": 1276.05,
    "c": 1278.15,
    "v": 517662
  },
  {
    "t": "2024-12-11T14:30:00+05:30",
    "o": 1279.05,
    "h": 1280.45,
    "l": 1276.85,
    "c": 1277.4,
    "v": 398336
  },
  {
    "t": "2024-12-11T14:15:00+05:30",
    "o": 1280.2,
    "h": 1280.4,
    "l": 1278.7,
    "c": 1279.2,
    "v": 329964
  },
  {
    "t": "2024-12-11T14:00:00+05:30",
    "o": 1281.65,
    "h": 1282.1,
    "l": 1279.15,
    "c": 1280.05,
    "v": 339268
  },
  {
    "t": "2024-12-11T13:45:00+05:30",
    "o": 1281.15,
    "h": 1284.5,
    "l": 1280.9,
    "c": 1281.7,
    "v": 367768
  },
  {
    "t": "2024-12-11T13:30:00+05:30",
    "o": 1283.5,
    "h": 1285,
    "l": 1279.7,
    "c": 1280.95,
    "v": 584558
  },
  {
    "t": "2024-12-11T13:15:00+05:30",
    "o": 1283.2,
    "h": 1283.8,
    "l": 1281.9,
    "c": 1283.65,
    "v": 375466
  },
  {
    "t": "2024-12-11T13:00:00+05:30",
    "o": 1282.9,
    "h": 1284,
    "l": 1282.1,
    "c": 1283.2,
    "v": 189328
  },
  {
    "t": "2024-12-11T12:45:00+05:30",
    "o": 1283.15,
    "h": 1284,
    "l": 1281.6,
    "c": 1282.75,
    "v": 411582
  },
  {
    "t": "2024-12-11T12:30:00+05:30",
    "o": 1283.15,
    "h": 1284.35,
    "l": 1282,
    "c": 1283.25,
    "v": 257043
  },
  {
    "t": "2024-12-11T12:15:00+05:30",
    "o": 1283.95,
    "h": 1284.7,
    "l": 1282.6,
    "c": 1283.15,
    "v": 260552
  },
  {
    "t": "2024-12-11T12:00:00+05:30",
    "o": 1286,
    "h": 1288,
    "l": 1283.8,
    "c": 1284,
    "v": 719930
  },
  {
    "t": "2024-12-11T11:45:00+05:30",
    "o": 1286.4,
    "h": 1286.7,
    "l": 1285,
    "c": 1286,
    "v": 264489
  },
  {
    "t": "2024-12-11T11:30:00+05:30",
    "o": 1284.7,
    "h": 1287,
    "l": 1283,
    "c": 1286.25,
    "v": 498722
  },
  {
    "t": "2024-12-11T11:15:00+05:30",
    "o": 1282.25,
    "h": 1285.4,
    "l": 1281.75,
    "c": 1284.9,
    "v": 462594
  },
  {
    "t": "2024-12-11T11:00:00+05:30",
    "o": 1283.6,
    "h": 1284.65,
    "l": 1282.25,
    "c": 1282.45,
    "v": 238824
  },
  {
    "t": "2024-12-11T10:45:00+05:30",
    "o": 1284.25,
    "h": 1285.65,
    "l": 1283.25,
    "c": 1283.6,
    "v": 283405
  },
  {
    "t": "2024-12-11T10:30:00+05:30",
    "o": 1283.6,
    "h": 1285.3,
    "l": 1281.55,
    "c": 1284.25,
    "v": 480791
  },
  {
    "t": "2024-12-11T10:15:00+05:30",
    "o": 1285,
    "h": 1286.3,
    "l": 1281,
    "c": 1283.6,
    "v": 408941
  },
  {
    "t": "2024-12-11T10:00:00+05:30",
    "o": 1285.95,
    "h": 1286.3,
    "l": 1283,
    "c": 1285.05,
    "v": 316014
  },
  {
    "t": "2024-12-11T09:45:00+05:30",
    "o": 1285.2,
    "h": 1286.4,
    "l": 1283.3,
    "c": 1286.05,
    "v": 430718
  },
  {
    "t": "2024-12-11T09:30:00+05:30",
    "o": 1288.4,
    "h": 1289.5,
    "l": 1284.3,
    "c": 1285.2,
    "v": 439401
  },
  {
    "t": "2024-12-11T09:15:00+05:30",
    "o": 1285,
    "h": 1290,
    "l": 1285,
    "c": 1288.5,
    "v": 627213
  },
  {
    "t": "2024-12-10T15:15:00+05:30",
    "o": 1284.8,
    "h": 1286.25,
    "l": 1284,
    "c": 1285.95,
    "v": 1430141
  },
  {
    "t": "2024-12-10T15:00:00+05:30",
    "o": 1282.5,
    "h": 1287.6,
    "l": 1282.4,
    "c": 1284.8,
    "v": 1888618
  },
  {
    "t": "2024-12-10T14:45:00+05:30",
    "o": 1281.45,
    "h": 1282.75,
    "l": 1281.15,
    "c": 1282.4,
    "v": 551320
  },
  {
    "t": "2024-12-10T14:30:00+05:30",
    "o": 1283.2,
    "h": 1283.3,
    "l": 1281,
    "c": 1281.5,
    "v": 426223
  },
  {
    "t": "2024-12-10T14:15:00+05:30",
    "o": 1282,
    "h": 1283.3,
    "l": 1281.05,
    "c": 1283.3,
    "v": 446292
  },
  {
    "t": "2024-12-10T14:00:00+05:30",
    "o": 1281.5,
    "h": 1282.5,
    "l": 1280.7,
    "c": 1282,
    "v": 347005
  },
  {
    "t": "2024-12-10T13:45:00+05:30",
    "o": 1281.15,
    "h": 1282.05,
    "l": 1280.2,
    "c": 1281.6,
    "v": 367673
  },
  {
    "t": "2024-12-10T13:30:00+05:30",
    "o": 1282.15,
    "h": 1285.95,
    "l": 1281,
    "c": 1281.15,
    "v": 526916
  },
  {
    "t": "2024-12-10T13:15:00+05:30",
    "o": 1282.2,
    "h": 1283.45,
    "l": 1280.7,
    "c": 1282.2,
    "v": 507403
  },
  {
    "t": "2024-12-10T13:00:00+05:30",
    "o": 1284.45,
    "h": 1284.6,
    "l": 1282,
    "c": 1282.15,
    "v": 355285
  },
  {
    "t": "2024-12-10T12:45:00+05:30",
    "o": 1283.25,
    "h": 1284.85,
    "l": 1282.4,
    "c": 1284.4,
    "v": 465987
  },
  {
    "t": "2024-12-10T12:30:00+05:30",
    "o": 1285.55,
    "h": 1285.6,
    "l": 1281.7,
    "c": 1283.25,
    "v": 725961
  },
  {
    "t": "2024-12-10T12:15:00+05:30",
    "o": 1288.45,
    "h": 1288.45,
    "l": 1285,
    "c": 1285.6,
    "v": 589882
  },
  {
    "t": "2024-12-10T12:00:00+05:30",
    "o": 1288.65,
    "h": 1291.8,
    "l": 1288.2,
    "c": 1288.4,
    "v": 449851
  },
  {
    "t": "2024-12-10T11:45:00+05:30",
    "o": 1292.8,
    "h": 1293,
    "l": 1288.5,
    "c": 1288.65,
    "v": 352051
  },
  {
    "t": "2024-12-10T11:30:00+05:30",
    "o": 1290.05,
    "h": 1293.45,
    "l": 1290,
    "c": 1292.85,
    "v": 378144
  },
  {
    "t": "2024-12-10T11:15:00+05:30",
    "o": 1289.45,
    "h": 1290.6,
    "l": 1289,
    "c": 1290.05,
    "v": 401919
  },
  {
    "t": "2024-12-10T11:00:00+05:30",
    "o": 1288.2,
    "h": 1289.5,
    "l": 1287.55,
    "c": 1289.45,
    "v": 414483
  },
  {
    "t": "2024-12-10T10:45:00+05:30",
    "o": 1286,
    "h": 1288.55,
    "l": 1285.6,
    "c": 1288.4,
    "v": 520937
  },
  {
    "t": "2024-12-10T10:30:00+05:30",
    "o": 1288.5,
    "h": 1288.55,
    "l": 1286,
    "c": 1286,
    "v": 484155
  },
  {
    "t": "2024-12-10T10:15:00+05:30",
    "o": 1288.5,
    "h": 1290.35,
    "l": 1287.35,
    "c": 1288.5,
    "v": 500292
  },
  {
    "t": "2024-12-10T10:00:00+05:30",
    "o": 1290.9,
    "h": 1291.55,
    "l": 1288.15,
    "c": 1288.5,
    "v": 486125
  },
  {
    "t": "2024-12-10T09:45:00+05:30",
    "o": 1290.45,
    "h": 1291.3,
    "l": 1288.65,
    "c": 1290.75,
    "v": 529186
  },
  {
    "t": "2024-12-10T09:30:00+05:30",
    "o": 1288.5,
    "h": 1291.9,
    "l": 1288.05,
    "c": 1290.6,
    "v": 705913
  },
  {
    "t": "2024-12-10T09:15:00+05:30",
    "o": 1289.25,
    "h": 1294.9,
    "l": 1286,
    "c": 1288.5,
    "v": 1836951
  },
  {
    "t": "2024-12-09T15:15:00+05:30",
    "o": 1293.55,
    "h": 1296.95,
    "l": 1293.1,
    "c": 1296.4,
    "v": 1442056
  },
  {
    "t": "2024-12-09T15:00:00+05:30",
    "o": 1295.7,
    "h": 1296.1,
    "l": 1293.5,
    "c": 1293.55,
    "v": 1428131
  },
  {
    "t": "2024-12-09T14:45:00+05:30",
    "o": 1297.75,
    "h": 1300.9,
    "l": 1295,
    "c": 1295.75,
    "v": 540688
  },
  {
    "t": "2024-12-09T14:30:00+05:30",
    "o": 1297.5,
    "h": 1298.85,
    "l": 1296.05,
    "c": 1297.75,
    "v": 487093
  },
  {
    "t": "2024-12-09T14:15:00+05:30",
    "o": 1299,
    "h": 1299,
    "l": 1297,
    "c": 1297.55,
    "v": 443193
  },
  {
    "t": "2024-12-09T14:00:00+05:30",
    "o": 1301.3,
    "h": 1301.5,
    "l": 1298.35,
    "c": 1299,
    "v": 637797
  },
  {
    "t": "2024-12-09T13:45:00+05:30",
    "o": 1302.4,
    "h": 1302.55,
    "l": 1301.05,
    "c": 1301.25,
    "v": 450668
  },
  {
    "t": "2024-12-09T13:30:00+05:30",
    "o": 1303.6,
    "h": 1304.6,
    "l": 1301.6,
    "c": 1302.4,
    "v": 448462
  },
  {
    "t": "2024-12-09T13:15:00+05:30",
    "o": 1305.35,
    "h": 1305.7,
    "l": 1303.5,
    "c": 1303.6,
    "v": 310925
  },
  {
    "t": "2024-12-09T13:00:00+05:30",
    "o": 1305.5,
    "h": 1305.75,
    "l": 1304.35,
    "c": 1305.35,
    "v": 413772
  },
  {
    "t": "2024-12-09T12:45:00+05:30",
    "o": 1305.55,
    "h": 1306.8,
    "l": 1305,
    "c": 1305.4,
    "v": 253762
  },
  {
    "t": "2024-12-09T12:30:00+05:30",
    "o": 1308.3,
    "h": 1308.45,
    "l": 1305.2,
    "c": 1305.65,
    "v": 339360
  },
  {
    "t": "2024-12-09T12:15:00+05:30",
    "o": 1309.5,
    "h": 1311.65,
    "l": 1308.15,
    "c": 1308.3,
    "v": 345232
  },
  {
    "t": "2024-12-09T12:00:00+05:30",
    "o": 1309.2,
    "h": 1310,
    "l": 1308.05,
    "c": 1309.65,
    "v": 319261
  },
  {
    "t": "2024-12-09T11:45:00+05:30",
    "o": 1309.6,
    "h": 1310.05,
    "l": 1307.6,
    "c": 1309.2,
    "v": 305052
  },
  {
    "t": "2024-12-09T11:30:00+05:30",
    "o": 1309.55,
    "h": 1310.05,
    "l": 1308.05,
    "c": 1309.6,
    "v": 400053
  },
  {
    "t": "2024-12-09T11:15:00+05:30",
    "o": 1307.95,
    "h": 1309.65,
    "l": 1306.25,
    "c": 1309.55,
    "v": 489160
  },
  {
    "t": "2024-12-09T11:00:00+05:30",
    "o": 1308.2,
    "h": 1309.85,
    "l": 1306.4,
    "c": 1307.95,
    "v": 520420
  },
  {
    "t": "2024-12-09T10:45:00+05:30",
    "o": 1308.2,
    "h": 1310.95,
    "l": 1307.7,
    "c": 1308.2,
    "v": 571017
  },
  {
    "t": "2024-12-09T10:30:00+05:30",
    "o": 1309.3,
    "h": 1309.9,
    "l": 1308.1,
    "c": 1308.2,
    "v": 413025
  },
  {
    "t": "2024-12-09T10:15:00+05:30",
    "o": 1307.15,
    "h": 1310.2,
    "l": 1307,
    "c": 1309.3,
    "v": 500176
  },
  {
    "t": "2024-12-09T10:00:00+05:30",
    "o": 1309.75,
    "h": 1310.1,
    "l": 1307,
    "c": 1307.1,
    "v": 469230
  },
  {
    "t": "2024-12-09T09:45:00+05:30",
    "o": 1312,
    "h": 1314.75,
    "l": 1309.15,
    "c": 1309.25,
    "v": 623345
  },
  {
    "t": "2024-12-09T09:30:00+05:30",
    "o": 1311.05,
    "h": 1313.75,
    "l": 1309.2,
    "c": 1312,
    "v": 706043
  },
  {
    "t": "2024-12-09T09:15:00+05:30",
    "o": 1303,
    "h": 1315,
    "l": 1303,
    "c": 1311.05,
    "v": 1629715
  },
  {
    "t": "2024-12-06T15:15:00+05:30",
    "o": 1312.15,
    "h": 1312.9,
    "l": 1310.7,
    "c": 1311.6,
    "v": 1112278
  },
  {
    "t": "2024-12-06T15:00:00+05:30",
    "o": 1311.8,
    "h": 1313.8,
    "l": 1310,
    "c": 1312,
    "v": 1338241
  },
  {
    "t": "2024-12-06T14:45:00+05:30",
    "o": 1313.35,
    "h": 1314.9,
    "l": 1311.7,
    "c": 1311.8,
    "v": 476729
  },
  {
    "t": "2024-12-06T14:30:00+05:30",
    "o": 1311.75,
    "h": 1313.5,
    "l": 1310,
    "c": 1313.5,
    "v": 329700
  },
  {
    "t": "2024-12-06T14:15:00+05:30",
    "o": 1313.2,
    "h": 1313.45,
    "l": 1310.55,
    "c": 1311.75,
    "v": 282840
  },
  {
    "t": "2024-12-06T14:00:00+05:30",
    "o": 1312,
    "h": 1314,
    "l": 1311.5,
    "c": 1312.85,
    "v": 241254
  },
  {
    "t": "2024-12-06T13:45:00+05:30",
    "o": 1312.75,
    "h": 1313.35,
    "l": 1311,
    "c": 1312,
    "v": 181841
  },
  {
    "t": "2024-12-06T13:30:00+05:30",
    "o": 1313.35,
    "h": 1314.25,
    "l": 1311,
    "c": 1312.75,
    "v": 352994
  },
  {
    "t": "2024-12-06T13:15:00+05:30",
    "o": 1315.7,
    "h": 1315.9,
    "l": 1313.1,
    "c": 1313.35,
    "v": 321585
  },
  {
    "t": "2024-12-06T13:00:00+05:30",
    "o": 1315.95,
    "h": 1316.4,
    "l": 1315.1,
    "c": 1315.6,
    "v": 200382
  },
  {
    "t": "2024-12-06T12:45:00+05:30",
    "o": 1317.65,
    "h": 1318.2,
    "l": 1315.5,
    "c": 1315.95,
    "v": 164936
  },
  {
    "t": "2024-12-06T12:30:00+05:30",
    "o": 1316.5,
    "h": 1318.2,
    "l": 1316,
    "c": 1317.65,
    "v": 127455
  },
  {
    "t": "2024-12-06T12:15:00+05:30",
    "o": 1316.05,
    "h": 1316.8,
    "l": 1315,
    "c": 1316.5,
    "v": 143016
  },
  {
    "t": "2024-12-06T12:00:00+05:30",
    "o": 1316.7,
    "h": 1317.2,
    "l": 1315.1,
    "c": 1316.1,
    "v": 219287
  },
  {
    "t": "2024-12-06T11:45:00+05:30",
    "o": 1315.5,
    "h": 1317.45,
    "l": 1315.05,
    "c": 1316.7,
    "v": 258603
  },
  {
    "t": "2024-12-06T11:30:00+05:30",
    "o": 1316.4,
    "h": 1317.3,
    "l": 1314,
    "c": 1315.5,
    "v": 349708
  },
  {
    "t": "2024-12-06T11:15:00+05:30",
    "o": 1317.4,
    "h": 1318.3,
    "l": 1316.05,
    "c": 1316.35,
    "v": 316593
  },
  {
    "t": "2024-12-06T11:00:00+05:30",
    "o": 1317.85,
    "h": 1320.7,
    "l": 1317.1,
    "c": 1317.4,
    "v": 230485
  },
  {
    "t": "2024-12-06T10:45:00+05:30",
    "o": 1317,
    "h": 1319.35,
    "l": 1315.65,
    "c": 1317.85,
    "v": 281031
  },
  {
    "t": "2024-12-06T10:30:00+05:30",
    "o": 1315.45,
    "h": 1317.1,
    "l": 1314.2,
    "c": 1317,
    "v": 202676
  },
  {
    "t": "2024-12-06T10:15:00+05:30",
    "o": 1316.1,
    "h": 1317.4,
    "l": 1314.15,
    "c": 1315.45,
    "v": 337085
  },
  {
    "t": "2024-12-06T10:00:00+05:30",
    "o": 1316.35,
    "h": 1319.5,
    "l": 1314.25,
    "c": 1315.75,
    "v": 373144
  },
  {
    "t": "2024-12-06T09:45:00+05:30",
    "o": 1319.1,
    "h": 1319.35,
    "l": 1315.05,
    "c": 1316.1,
    "v": 249092
  },
  {
    "t": "2024-12-06T09:30:00+05:30",
    "o": 1317,
    "h": 1319.5,
    "l": 1315.05,
    "c": 1319.2,
    "v": 266355
  },
  {
    "t": "2024-12-06T09:15:00+05:30",
    "o": 1323.9,
    "h": 1323.9,
    "l": 1315.65,
    "c": 1317.3,
    "v": 599121
  },
  {
    "t": "2024-12-05T15:15:00+05:30",
    "o": 1323.35,
    "h": 1325.55,
    "l": 1320.05,
    "c": 1320.9,
    "v": 1148798
  },
  {
    "t": "2024-12-05T15:00:00+05:30",
    "o": 1314.25,
    "h": 1326,
    "l": 1313.3,
    "c": 1323.45,
    "v": 2021129
  },
  {
    "t": "2024-12-05T14:45:00+05:30",
    "o": 1327.9,
    "h": 1329.95,
    "l": 1312.2,
    "c": 1314.25,
    "v": 2102351
  },
  {
    "t": "2024-12-05T14:30:00+05:30",
    "o": 1327.9,
    "h": 1329.9,
    "l": 1324.2,
    "c": 1327.9,
    "v": 1479009
  },
  {
    "t": "2024-12-05T14:15:00+05:30",
    "o": 1323.35,
    "h": 1328,
    "l": 1323.05,
    "c": 1327.95,
    "v": 1061863
  },
  {
    "t": "2024-12-05T14:00:00+05:30",
    "o": 1322.35,
    "h": 1325.65,
    "l": 1320,
    "c": 1323.35,
    "v": 747389
  },
  {
    "t": "2024-12-05T13:45:00+05:30",
    "o": 1320.95,
    "h": 1323,
    "l": 1319.45,
    "c": 1322.55,
    "v": 302431
  },
  {
    "t": "2024-12-05T13:30:00+05:30",
    "o": 1317,
    "h": 1322.95,
    "l": 1316.95,
    "c": 1320.95,
    "v": 572349
  },
  {
    "t": "2024-12-05T13:15:00+05:30",
    "o": 1321.25,
    "h": 1322.45,
    "l": 1316.45,
    "c": 1317,
    "v": 424220
  },
  {
    "t": "2024-12-05T13:00:00+05:30",
    "o": 1319.5,
    "h": 1321.85,
    "l": 1318.05,
    "c": 1321.25,
    "v": 236576
  },
  {
    "t": "2024-12-05T12:45:00+05:30",
    "o": 1320.5,
    "h": 1321,
    "l": 1318,
    "c": 1319.4,
    "v": 211553
  },
  {
    "t": "2024-12-05T12:30:00+05:30",
    "o": 1321.85,
    "h": 1322.8,
    "l": 1318.65,
    "c": 1320.5,
    "v": 316092
  },
  {
    "t": "2024-12-05T12:15:00+05:30",
    "o": 1321.7,
    "h": 1324.75,
    "l": 1320.1,
    "c": 1321.85,
    "v": 832487
  },
  {
    "t": "2024-12-05T12:00:00+05:30",
    "o": 1311.6,
    "h": 1322.9,
    "l": 1311.35,
    "c": 1321.55,
    "v": 1249138
  },
  {
    "t": "2024-12-05T11:45:00+05:30",
    "o": 1309.75,
    "h": 1311.95,
    "l": 1309,
    "c": 1311.95,
    "v": 193107
  },
  {
    "t": "2024-12-05T11:30:00+05:30",
    "o": 1309.9,
    "h": 1310,
    "l": 1307.1,
    "c": 1309.3,
    "v": 131590
  },
  {
    "t": "2024-12-05T11:15:00+05:30",
    "o": 1310.7,
    "h": 1311.35,
    "l": 1308.55,
    "c": 1309.9,
    "v": 183594
  },
  {
    "t": "2024-12-05T11:00:00+05:30",
    "o": 1309.5,
    "h": 1311.85,
    "l": 1308.4,
    "c": 1310.6,
    "v": 266545
  },
  {
    "t": "2024-12-05T10:45:00+05:30",
    "o": 1312.2,
    "h": 1314.95,
    "l": 1306.3,
    "c": 1309.65,
    "v": 452442
  },
  {
    "t": "2024-12-05T10:30:00+05:30",
    "o": 1310.95,
    "h": 1312.9,
    "l": 1309.5,
    "c": 1312.2,
    "v": 209556
  },
  {
    "t": "2024-12-05T10:15:00+05:30",
    "o": 1307.9,
    "h": 1311.5,
    "l": 1306.15,
    "c": 1310.95,
    "v": 365479
  },
  {
    "t": "2024-12-05T10:00:00+05:30",
    "o": 1311.35,
    "h": 1312.9,
    "l": 1307.6,
    "c": 1307.95,
    "v": 223777
  },
  {
    "t": "2024-12-05T09:45:00+05:30",
    "o": 1313.1,
    "h": 1314,
    "l": 1307.05,
    "c": 1311.35,
    "v": 429698
  },
  {
    "t": "2024-12-05T09:30:00+05:30",
    "o": 1313.45,
    "h": 1315.95,
    "l": 1310.4,
    "c": 1313.1,
    "v": 363541
  },
  {
    "t": "2024-12-05T09:15:00+05:30",
    "o": 1314.35,
    "h": 1320.45,
    "l": 1306.8,
    "c": 1313.5,
    "v": 1192062
  },
  {
    "t": "2024-12-04T15:15:00+05:30",
    "o": 1307.85,
    "h": 1310.8,
    "l": 1306,
    "c": 1309.5,
    "v": 1070311
  },
  {
    "t": "2024-12-04T15:00:00+05:30",
    "o": 1306,
    "h": 1310.8,
    "l": 1304.7,
    "c": 1307.9,
    "v": 1075316
  },
  {
    "t": "2024-12-04T14:45:00+05:30",
    "o": 1306.65,
    "h": 1306.7,
    "l": 1304.05,
    "c": 1306,
    "v": 613867
  },
  {
    "t": "2024-12-04T14:30:00+05:30",
    "o": 1307.95,
    "h": 1307.95,
    "l": 1305.1,
    "c": 1306.65,
    "v": 524577
  },
  {
    "t": "2024-12-04T14:15:00+05:30",
    "o": 1311.45,
    "h": 1311.7,
    "l": 1306.25,
    "c": 1307.95,
    "v": 477222
  },
  {
    "t": "2024-12-04T14:00:00+05:30",
    "o": 1313.05,
    "h": 1313.25,
    "l": 1311.05,
    "c": 1311.4,
    "v": 221190
  },
  {
    "t": "2024-12-04T13:45:00+05:30",
    "o": 1311.2,
    "h": 1313.5,
    "l": 1311,
    "c": 1312.95,
    "v": 260339
  },
  {
    "t": "2024-12-04T13:30:00+05:30",
    "o": 1309.55,
    "h": 1313.65,
    "l": 1309.1,
    "c": 1311.4,
    "v": 434210
  },
  {
    "t": "2024-12-04T13:15:00+05:30",
    "o": 1309.3,
    "h": 1310,
    "l": 1308,
    "c": 1309.55,
    "v": 310536
  },
  {
    "t": "2024-12-04T13:00:00+05:30",
    "o": 1311.05,
    "h": 1311.7,
    "l": 1309.1,
    "c": 1309.4,
    "v": 345628
  },
  {
    "t": "2024-12-04T12:45:00+05:30",
    "o": 1308.95,
    "h": 1312,
    "l": 1308.6,
    "c": 1311.1,
    "v": 253176
  },
  {
    "t": "2024-12-04T12:30:00+05:30",
    "o": 1312.7,
    "h": 1312.75,
    "l": 1308.25,
    "c": 1308.9,
    "v": 210942
  },
  {
    "t": "2024-12-04T12:15:00+05:30",
    "o": 1310.4,
    "h": 1313,
    "l": 1310,
    "c": 1312.7,
    "v": 264878
  },
  {
    "t": "2024-12-04T12:00:00+05:30",
    "o": 1309.45,
    "h": 1312.35,
    "l": 1305.8,
    "c": 1310.4,
    "v": 4021750
  },
  {
    "t": "2024-12-04T11:45:00+05:30",
    "o": 1314.15,
    "h": 1314.2,
    "l": 1305.5,
    "c": 1309.45,
    "v": 613234
  },
  {
    "t": "2024-12-04T11:30:00+05:30",
    "o": 1313.7,
    "h": 1315.5,
    "l": 1313.45,
    "c": 1314.05,
    "v": 194640
  },
  {
    "t": "2024-12-04T11:15:00+05:30",
    "o": 1312,
    "h": 1313.95,
    "l": 1311.75,
    "c": 1313.8,
    "v": 178844
  },
  {
    "t": "2024-12-04T11:00:00+05:30",
    "o": 1313.4,
    "h": 1314,
    "l": 1311.3,
    "c": 1312.05,
    "v": 985069
  },
  {
    "t": "2024-12-04T10:45:00+05:30",
    "o": 1313.25,
    "h": 1316,
    "l": 1311.3,
    "c": 1313.4,
    "v": 4891457
  },
  {
    "t": "2024-12-04T10:30:00+05:30",
    "o": 1314.45,
    "h": 1315.9,
    "l": 1313.1,
    "c": 1313.25,
    "v": 188656
  },
  {
    "t": "2024-12-04T10:15:00+05:30",
    "o": 1317.75,
    "h": 1318,
    "l": 1312.65,
    "c": 1314.6,
    "v": 316020
  },
  {
    "t": "2024-12-04T10:00:00+05:30",
    "o": 1317.5,
    "h": 1319,
    "l": 1315.95,
    "c": 1317.75,
    "v": 238407
  },
  {
    "t": "2024-12-04T09:45:00+05:30",
    "o": 1317,
    "h": 1318.85,
    "l": 1313.4,
    "c": 1317.7,
    "v": 427789
  },
  {
    "t": "2024-12-04T09:30:00+05:30",
    "o": 1319,
    "h": 1319.05,
    "l": 1315.1,
    "c": 1317,
    "v": 571130
  },
  {
    "t": "2024-12-04T09:15:00+05:30",
    "o": 1326,
    "h": 1328.4,
    "l": 1315.45,
    "c": 1319,
    "v": 813538
  },
  {
    "t": "2024-12-03T15:15:00+05:30",
    "o": 1324.15,
    "h": 1325.15,
    "l": 1321.4,
    "c": 1325.05,
    "v": 1690307
  },
  {
    "t": "2024-12-03T15:00:00+05:30",
    "o": 1322.55,
    "h": 1324.25,
    "l": 1321.15,
    "c": 1324.15,
    "v": 1375990
  },
  {
    "t": "2024-12-03T14:45:00+05:30",
    "o": 1321.75,
    "h": 1323,
    "l": 1321.2,
    "c": 1322.6,
    "v": 498850
  },
  {
    "t": "2024-12-03T14:30:00+05:30",
    "o": 1320.15,
    "h": 1321.85,
    "l": 1319.35,
    "c": 1321.75,
    "v": 875628
  },
  {
    "t": "2024-12-03T14:15:00+05:30",
    "o": 1322,
    "h": 1322.75,
    "l": 1319.7,
    "c": 1320.1,
    "v": 670289
  },
  {
    "t": "2024-12-03T14:00:00+05:30",
    "o": 1324.6,
    "h": 1325,
    "l": 1321.5,
    "c": 1322,
    "v": 532929
  },
  {
    "t": "2024-12-03T13:45:00+05:30",
    "o": 1323.4,
    "h": 1325.5,
    "l": 1323.2,
    "c": 1324.45,
    "v": 707824
  },
  {
    "t": "2024-12-03T13:30:00+05:30",
    "o": 1321.7,
    "h": 1325.35,
    "l": 1321.25,
    "c": 1323.5,
    "v": 374016
  },
  {
    "t": "2024-12-03T13:15:00+05:30",
    "o": 1323.1,
    "h": 1323.9,
    "l": 1321.5,
    "c": 1321.75,
    "v": 260851
  },
  {
    "t": "2024-12-03T13:00:00+05:30",
    "o": 1324.65,
    "h": 1324.8,
    "l": 1323,
    "c": 1323.15,
    "v": 220326
  },
  {
    "t": "2024-12-03T12:45:00+05:30",
    "o": 1324.4,
    "h": 1325,
    "l": 1323.55,
    "c": 1324.7,
    "v": 275752
  },
  {
    "t": "2024-12-03T12:30:00+05:30",
    "o": 1319.95,
    "h": 1324.75,
    "l": 1319.7,
    "c": 1324.45,
    "v": 326605
  },
  {
    "t": "2024-12-03T12:15:00+05:30",
    "o": 1324.15,
    "h": 1324.9,
    "l": 1319.2,
    "c": 1320,
    "v": 531497
  },
  {
    "t": "2024-12-03T12:00:00+05:30",
    "o": 1325.45,
    "h": 1325.8,
    "l": 1322.15,
    "c": 1323.95,
    "v": 477913
  },
  {
    "t": "2024-12-03T11:45:00+05:30",
    "o": 1324.1,
    "h": 1325.9,
    "l": 1322,
    "c": 1325.55,
    "v": 541605
  },
  {
    "t": "2024-12-03T11:30:00+05:30",
    "o": 1322.35,
    "h": 1326.8,
    "l": 1322.2,
    "c": 1324.1,
    "v": 670081
  },
  {
    "t": "2024-12-03T11:15:00+05:30",
    "o": 1320.95,
    "h": 1323.45,
    "l": 1320.45,
    "c": 1322.35,
    "v": 283307
  },
  {
    "t": "2024-12-03T11:00:00+05:30",
    "o": 1322.45,
    "h": 1323.45,
    "l": 1320.2,
    "c": 1320.95,
    "v": 458371
  },
  {
    "t": "2024-12-03T10:45:00+05:30",
    "o": 1322.5,
    "h": 1324.45,
    "l": 1320.85,
    "c": 1322.45,
    "v": 950669
  },
  {
    "t": "2024-12-03T10:30:00+05:30",
    "o": 1320.5,
    "h": 1323.8,
    "l": 1320.35,
    "c": 1322.6,
    "v": 685060
  },
  {
    "t": "2024-12-03T10:15:00+05:30",
    "o": 1316.15,
    "h": 1320.9,
    "l": 1315.75,
    "c": 1320.4,
    "v": 630638
  },
  {
    "t": "2024-12-03T10:00:00+05:30",
    "o": 1317.95,
    "h": 1319,
    "l": 1315.95,
    "c": 1316.05,
    "v": 595071
  },
  {
    "t": "2024-12-03T09:45:00+05:30",
    "o": 1314.15,
    "h": 1318,
    "l": 1313.1,
    "c": 1317.9,
    "v": 946938
  },
  {
    "t": "2024-12-03T09:30:00+05:30",
    "o": 1309.95,
    "h": 1314.9,
    "l": 1307,
    "c": 1314.15,
    "v": 635700
  },
  {
    "t": "2024-12-03T09:15:00+05:30",
    "o": 1317,
    "h": 1317,
    "l": 1309,
    "c": 1309.7,
    "v": 1455523
  },
  {
    "t": "2024-12-02T15:15:00+05:30",
    "o": 1308.05,
    "h": 1311.35,
    "l": 1306.55,
    "c": 1310.6,
    "v": 1205261
  },
  {
    "t": "2024-12-02T15:00:00+05:30",
    "o": 1307.65,
    "h": 1310.2,
    "l": 1307,
    "c": 1308.15,
    "v": 1046471
  },
  {
    "t": "2024-12-02T14:45:00+05:30",
    "o": 1310.1,
    "h": 1311,
    "l": 1306.25,
    "c": 1307.65,
    "v": 386031
  },
  {
    "t": "2024-12-02T14:30:00+05:30",
    "o": 1308.2,
    "h": 1310.45,
    "l": 1308.2,
    "c": 1310.3,
    "v": 587854
  },
  {
    "t": "2024-12-02T14:15:00+05:30",
    "o": 1308.55,
    "h": 1309.45,
    "l": 1306.05,
    "c": 1308.3,
    "v": 346887
  },
  {
    "t": "2024-12-02T14:00:00+05:30",
    "o": 1307,
    "h": 1309.6,
    "l": 1306.65,
    "c": 1308.55,
    "v": 460551
  },
  {
    "t": "2024-12-02T13:45:00+05:30",
    "o": 1306.35,
    "h": 1307,
    "l": 1303.2,
    "c": 1307,
    "v": 287219
  },
  {
    "t": "2024-12-02T13:30:00+05:30",
    "o": 1300.35,
    "h": 1307,
    "l": 1300,
    "c": 1306.35,
    "v": 516683
  },
  {
    "t": "2024-12-02T13:15:00+05:30",
    "o": 1299.65,
    "h": 1304.2,
    "l": 1299.05,
    "c": 1300.35,
    "v": 430765
  },
  {
    "t": "2024-12-02T13:00:00+05:30",
    "o": 1300.1,
    "h": 1300.6,
    "l": 1298.5,
    "c": 1299.65,
    "v": 221821
  },
  {
    "t": "2024-12-02T12:45:00+05:30",
    "o": 1300.4,
    "h": 1302.5,
    "l": 1298.4,
    "c": 1300.1,
    "v": 345334
  },
  {
    "t": "2024-12-02T12:30:00+05:30",
    "o": 1297.45,
    "h": 1301,
    "l": 1295.5,
    "c": 1300.4,
    "v": 444793
  },
  {
    "t": "2024-12-02T12:15:00+05:30",
    "o": 1293.1,
    "h": 1297.95,
    "l": 1292.65,
    "c": 1297.55,
    "v": 218533
  },
  {
    "t": "2024-12-02T12:00:00+05:30",
    "o": 1296.9,
    "h": 1297.8,
    "l": 1293.1,
    "c": 1293.15,
    "v": 150898
  },
  {
    "t": "2024-12-02T11:45:00+05:30",
    "o": 1296.2,
    "h": 1297,
    "l": 1293.6,
    "c": 1297,
    "v": 159298
  },
  {
    "t": "2024-12-02T11:30:00+05:30",
    "o": 1295.45,
    "h": 1297.5,
    "l": 1292.85,
    "c": 1296.2,
    "v": 233763
  },
  {
    "t": "2024-12-02T11:15:00+05:30",
    "o": 1293.3,
    "h": 1297.45,
    "l": 1292.6,
    "c": 1295.25,
    "v": 302376
  },
  {
    "t": "2024-12-02T11:00:00+05:30",
    "o": 1291.65,
    "h": 1294.15,
    "l": 1291.25,
    "c": 1293.3,
    "v": 150096
  },
  {
    "t": "2024-12-02T10:45:00+05:30",
    "o": 1292.75,
    "h": 1296,
    "l": 1291.55,
    "c": 1292,
    "v": 231968
  },
  {
    "t": "2024-12-02T10:30:00+05:30",
    "o": 1293.95,
    "h": 1294.7,
    "l": 1290,
    "c": 1292.65,
    "v": 234948
  },
  {
    "t": "2024-12-02T10:15:00+05:30",
    "o": 1286.75,
    "h": 1295.6,
    "l": 1286.5,
    "c": 1293.95,
    "v": 538766
  },
  {
    "t": "2024-12-02T10:00:00+05:30",
    "o": 1285.85,
    "h": 1288.75,
    "l": 1283.8,
    "c": 1286.7,
    "v": 250194
  },
  {
    "t": "2024-12-02T09:45:00+05:30",
    "o": 1285.1,
    "h": 1287,
    "l": 1282.45,
    "c": 1286,
    "v": 446527
  },
  {
    "t": "2024-12-02T09:30:00+05:30",
    "o": 1278.8,
    "h": 1285.5,
    "l": 1278.65,
    "c": 1285.2,
    "v": 520582
  },
  {
    "t": "2024-12-02T09:15:00+05:30",
    "o": 1288,
    "h": 1291.4,
    "l": 1277.05,
    "c": 1278.8,
    "v": 1170317
  },
  {
    "t": "2024-11-29T15:15:00+05:30",
    "o": 1292.55,
    "h": 1293.7,
    "l": 1289.75,
    "c": 1291.5,
    "v": 1703384
  },
  {
    "t": "2024-11-29T15:00:00+05:30",
    "o": 1293.1,
    "h": 1294.8,
    "l": 1290.4,
    "c": 1292.55,
    "v": 1970910
  },
  {
    "t": "2024-11-29T14:45:00+05:30",
    "o": 1293.65,
    "h": 1294.8,
    "l": 1291,
    "c": 1293.1,
    "v": 430168
  },
  {
    "t": "2024-11-29T14:30:00+05:30",
    "o": 1292.5,
    "h": 1295.75,
    "l": 1291.35,
    "c": 1293.7,
    "v": 670213
  },
  {
    "t": "2024-11-29T14:15:00+05:30",
    "o": 1290.7,
    "h": 1293.5,
    "l": 1289.75,
    "c": 1292.2,
    "v": 463992
  },
  {
    "t": "2024-11-29T14:00:00+05:30",
    "o": 1292.6,
    "h": 1293.45,
    "l": 1290.15,
    "c": 1290.7,
    "v": 337229
  },
  {
    "t": "2024-11-29T13:45:00+05:30",
    "o": 1295.05,
    "h": 1295.7,
    "l": 1292.25,
    "c": 1292.85,
    "v": 284269
  },
  {
    "t": "2024-11-29T13:30:00+05:30",
    "o": 1296.45,
    "h": 1298.35,
    "l": 1294.8,
    "c": 1295.4,
    "v": 439437
  },
  {
    "t": "2024-11-29T13:15:00+05:30",
    "o": 1294.15,
    "h": 1298.8,
    "l": 1293.5,
    "c": 1296.5,
    "v": 442842
  },
  {
    "t": "2024-11-29T13:00:00+05:30",
    "o": 1292.95,
    "h": 1294.5,
    "l": 1291.1,
    "c": 1294.15,
    "v": 202298
  },
  {
    "t": "2024-11-29T12:45:00+05:30",
    "o": 1291.15,
    "h": 1293.8,
    "l": 1290.4,
    "c": 1292.95,
    "v": 213996
  },
  {
    "t": "2024-11-29T12:30:00+05:30",
    "o": 1293.45,
    "h": 1293.5,
    "l": 1291.05,
    "c": 1291.2,
    "v": 298624
  },
  {
    "t": "2024-11-29T12:15:00+05:30",
    "o": 1295.45,
    "h": 1296.15,
    "l": 1292.25,
    "c": 1293.45,
    "v": 197920
  },
  {
    "t": "2024-11-29T12:00:00+05:30",
    "o": 1292.8,
    "h": 1295.9,
    "l": 1292,
    "c": 1295.45,
    "v": 176866
  },
  {
    "t": "2024-11-29T11:45:00+05:30",
    "o": 1294.8,
    "h": 1295.6,
    "l": 1292.05,
    "c": 1292.9,
    "v": 236069
  },
  {
    "t": "2024-11-29T11:30:00+05:30",
    "o": 1298.1,
    "h": 1298.9,
    "l": 1294.2,
    "c": 1294.9,
    "v": 261938
  },
  {
    "t": "2024-11-29T11:15:00+05:30",
    "o": 1297.1,
    "h": 1298.75,
    "l": 1295.2,
    "c": 1298.1,
    "v": 280683
  },
  {
    "t": "2024-11-29T11:00:00+05:30",
    "o": 1297.65,
    "h": 1299.5,
    "l": 1296.05,
    "c": 1297.1,
    "v": 540848
  },
  {
    "t": "2024-11-29T10:45:00+05:30",
    "o": 1289.05,
    "h": 1298.75,
    "l": 1288.9,
    "c": 1297.85,
    "v": 861685
  },
  {
    "t": "2024-11-29T10:30:00+05:30",
    "o": 1283.05,
    "h": 1293,
    "l": 1282.75,
    "c": 1289.05,
    "v": 653017
  },
  {
    "t": "2024-11-29T10:15:00+05:30",
    "o": 1279.8,
    "h": 1284.95,
    "l": 1279,
    "c": 1283.1,
    "v": 303819
  },
  {
    "t": "2024-11-29T10:00:00+05:30",
    "o": 1283.6,
    "h": 1284.6,
    "l": 1279.5,
    "c": 1279.8,
    "v": 382368
  },
  {
    "t": "2024-11-29T09:45:00+05:30",
    "o": 1278.85,
    "h": 1283.75,
    "l": 1278.5,
    "c": 1283.75,
    "v": 268574
  },
  {
    "t": "2024-11-29T09:30:00+05:30",
    "o": 1281.45,
    "h": 1283,
    "l": 1278.25,
    "c": 1278.85,
    "v": 412141
  },
  {
    "t": "2024-11-29T09:15:00+05:30",
    "o": 1280,
    "h": 1281.95,
    "l": 1275.25,
    "c": 1281.45,
    "v": 953030
  },
  {
    "t": "2024-11-28T15:15:00+05:30",
    "o": 1269.7,
    "h": 1273.9,
    "l": 1269.05,
    "c": 1272.75,
    "v": 1589004
  },
  {
    "t": "2024-11-28T15:00:00+05:30",
    "o": 1272.9,
    "h": 1272.95,
    "l": 1269.2,
    "c": 1269.7,
    "v": 1635311
  },
  {
    "t": "2024-11-28T14:45:00+05:30",
    "o": 1274.35,
    "h": 1274.6,
    "l": 1272.05,
    "c": 1273,
    "v": 772759
  },
  {
    "t": "2024-11-28T14:30:00+05:30",
    "o": 1277.2,
    "h": 1279.9,
    "l": 1273.25,
    "c": 1273.75,
    "v": 720421
  },
  {
    "t": "2024-11-28T14:15:00+05:30",
    "o": 1277,
    "h": 1278.45,
    "l": 1273.4,
    "c": 1277.2,
    "v": 617567
  },
  {
    "t": "2024-11-28T14:00:00+05:30",
    "o": 1279.7,
    "h": 1283.9,
    "l": 1273.5,
    "c": 1276.85,
    "v": 822973
  },
  {
    "t": "2024-11-28T13:45:00+05:30",
    "o": 1277.5,
    "h": 1280.5,
    "l": 1274.7,
    "c": 1280,
    "v": 430836
  },
  {
    "t": "2024-11-28T13:30:00+05:30",
    "o": 1279.35,
    "h": 1279.55,
    "l": 1275.1,
    "c": 1277.5,
    "v": 411562
  },
  {
    "t": "2024-11-28T13:15:00+05:30",
    "o": 1279.6,
    "h": 1280.25,
    "l": 1278.85,
    "c": 1279.35,
    "v": 350581
  },
  {
    "t": "2024-11-28T13:00:00+05:30",
    "o": 1278.5,
    "h": 1280.4,
    "l": 1278,
    "c": 1279.75,
    "v": 353608
  },
  {
    "t": "2024-11-28T12:45:00+05:30",
    "o": 1283,
    "h": 1283.3,
    "l": 1278,
    "c": 1278.5,
    "v": 590063
  },
  {
    "t": "2024-11-28T12:30:00+05:30",
    "o": 1286.25,
    "h": 1286.35,
    "l": 1281.35,
    "c": 1283.1,
    "v": 452262
  },
  {
    "t": "2024-11-28T12:15:00+05:30",
    "o": 1285.9,
    "h": 1286.7,
    "l": 1284.25,
    "c": 1286.3,
    "v": 226117
  },
  {
    "t": "2024-11-28T12:00:00+05:30",
    "o": 1284.85,
    "h": 1286.75,
    "l": 1283.5,
    "c": 1285.9,
    "v": 233366
  },
  {
    "t": "2024-11-28T11:45:00+05:30",
    "o": 1282.7,
    "h": 1288.7,
    "l": 1282.1,
    "c": 1285,
    "v": 369632
  },
  {
    "t": "2024-11-28T11:30:00+05:30",
    "o": 1282.9,
    "h": 1283.7,
    "l": 1281,
    "c": 1282.7,
    "v": 334174
  },
  {
    "t": "2024-11-28T11:15:00+05:30",
    "o": 1284.4,
    "h": 1284.9,
    "l": 1282.05,
    "c": 1282.9,
    "v": 325837
  },
  {
    "t": "2024-11-28T11:00:00+05:30",
    "o": 1287.6,
    "h": 1287.85,
    "l": 1283.5,
    "c": 1284.45,
    "v": 263768
  },
  {
    "t": "2024-11-28T10:45:00+05:30",
    "o": 1285.85,
    "h": 1287.9,
    "l": 1283.1,
    "c": 1287.6,
    "v": 360754
  },
  {
    "t": "2024-11-28T10:30:00+05:30",
    "o": 1295.05,
    "h": 1295.5,
    "l": 1283.4,
    "c": 1285.85,
    "v": 1345067
  },
  {
    "t": "2024-11-28T10:15:00+05:30",
    "o": 1292.7,
    "h": 1296.6,
    "l": 1292,
    "c": 1295.05,
    "v": 381186
  },
  {
    "t": "2024-11-28T10:00:00+05:30",
    "o": 1291.35,
    "h": 1295.6,
    "l": 1291.25,
    "c": 1292.4,
    "v": 469691
  },
  {
    "t": "2024-11-28T09:45:00+05:30",
    "o": 1292.05,
    "h": 1292.45,
    "l": 1290.3,
    "c": 1291.55,
    "v": 370397
  },
  {
    "t": "2024-11-28T09:30:00+05:30",
    "o": 1290.2,
    "h": 1292.4,
    "l": 1289.5,
    "c": 1292.2,
    "v": 417064
  },
  {
    "t": "2024-11-28T09:15:00+05:30",
    "o": 1289.95,
    "h": 1293.2,
    "l": 1286.55,
    "c": 1290.3,
    "v": 1066476
  },
  {
    "t": "2024-11-27T15:15:00+05:30",
    "o": 1293.6,
    "h": 1294.25,
    "l": 1292.5,
    "c": 1293.4,
    "v": 569768
  },
  {
    "t": "2024-11-27T15:00:00+05:30",
    "o": 1294.8,
    "h": 1294.8,
    "l": 1291.3,
    "c": 1293.6,
    "v": 498949
  },
  {
    "t": "2024-11-27T14:45:00+05:30",
    "o": 1296.1,
    "h": 1296.45,
    "l": 1294.5,
    "c": 1294.85,
    "v": 326901
  },
  {
    "t": "2024-11-27T14:30:00+05:30",
    "o": 1298.25,
    "h": 1298.6,
    "l": 1295.2,
    "c": 1296.1,
    "v": 329275
  },
  {
    "t": "2024-11-27T14:15:00+05:30",
    "o": 1295.9,
    "h": 1298.7,
    "l": 1295,
    "c": 1298.05,
    "v": 375268
  },
  {
    "t": "2024-11-27T14:00:00+05:30",
    "o": 1298.35,
    "h": 1299.25,
    "l": 1295.1,
    "c": 1296.1,
    "v": 303232
  },
  {
    "t": "2024-11-27T13:45:00+05:30",
    "o": 1299.8,
    "h": 1301.9,
    "l": 1295,
    "c": 1298.35,
    "v": 446709
  },
  {
    "t": "2024-11-27T13:30:00+05:30",
    "o": 1301.85,
    "h": 1301.85,
    "l": 1298.35,
    "c": 1299.8,
    "v": 251762
  },
  {
    "t": "2024-11-27T13:15:00+05:30",
    "o": 1299.9,
    "h": 1303.85,
    "l": 1299.5,
    "c": 1301.65,
    "v": 476805
  },
  {
    "t": "2024-11-27T13:00:00+05:30",
    "o": 1298,
    "h": 1301,
    "l": 1297.5,
    "c": 1299.95,
    "v": 388677
  },
  {
    "t": "2024-11-27T12:45:00+05:30",
    "o": 1297.7,
    "h": 1298.25,
    "l": 1294.65,
    "c": 1297.9,
    "v": 276070
  },
  {
    "t": "2024-11-27T12:30:00+05:30",
    "o": 1293.6,
    "h": 1298.9,
    "l": 1293.1,
    "c": 1297.7,
    "v": 448862
  },
  {
    "t": "2024-11-27T12:15:00+05:30",
    "o": 1291.2,
    "h": 1294.5,
    "l": 1291,
    "c": 1293.7,
    "v": 205887
  },
  {
    "t": "2024-11-27T12:00:00+05:30",
    "o": 1290.7,
    "h": 1292.55,
    "l": 1289,
    "c": 1291.2,
    "v": 246278
  },
  {
    "t": "2024-11-27T11:45:00+05:30",
    "o": 1292.4,
    "h": 1292.65,
    "l": 1288.55,
    "c": 1290.7,
    "v": 483992
  },
  {
    "t": "2024-11-27T11:30:00+05:30",
    "o": 1294.25,
    "h": 1295.35,
    "l": 1292.2,
    "c": 1292.5,
    "v": 280022
  },
  {
    "t": "2024-11-27T11:15:00+05:30",
    "o": 1294.25,
    "h": 1294.3,
    "l": 1293,
    "c": 1294.3,
    "v": 162433
  },
  {
    "t": "2024-11-27T11:00:00+05:30",
    "o": 1292.55,
    "h": 1295.6,
    "l": 1292.05,
    "c": 1294.2,
    "v": 257570
  },
  {
    "t": "2024-11-27T10:45:00+05:30",
    "o": 1289.8,
    "h": 1292.8,
    "l": 1289.5,
    "c": 1292.75,
    "v": 194960
  },
  {
    "t": "2024-11-27T10:30:00+05:30",
    "o": 1291.3,
    "h": 1291.9,
    "l": 1289.1,
    "c": 1289.8,
    "v": 195356
  },
  {
    "t": "2024-11-27T10:15:00+05:30",
    "o": 1291.5,
    "h": 1292,
    "l": 1290.3,
    "c": 1291.35,
    "v": 168954
  },
  {
    "t": "2024-11-27T10:00:00+05:30",
    "o": 1291.75,
    "h": 1294,
    "l": 1289.65,
    "c": 1291.5,
    "v": 302943
  },
  {
    "t": "2024-11-27T09:45:00+05:30",
    "o": 1286.75,
    "h": 1292.75,
    "l": 1286.1,
    "c": 1291.8,
    "v": 776614
  },
  {
    "t": "2024-11-27T09:30:00+05:30",
    "o": 1289.75,
    "h": 1291.3,
    "l": 1286,
    "c": 1286.75,
    "v": 489533
  },
  {
    "t": "2024-11-27T09:15:00+05:30",
    "o": 1293.5,
    "h": 1293.5,
    "l": 1286.1,
    "c": 1289.75,
    "v": 1011261
  },
  {
    "t": "2024-11-26T15:15:00+05:30",
    "o": 1296.55,
    "h": 1296.8,
    "l": 1294.85,
    "c": 1295.6,
    "v": 997765
  },
  {
    "t": "2024-11-26T15:00:00+05:30",
    "o": 1297,
    "h": 1297.2,
    "l": 1292.7,
    "c": 1296.55,
    "v": 869101
  },
  {
    "t": "2024-11-26T14:45:00+05:30",
    "o": 1295.35,
    "h": 1297.85,
    "l": 1295,
    "c": 1297,
    "v": 481532
  },
  {
    "t": "2024-11-26T14:30:00+05:30",
    "o": 1291.3,
    "h": 1295.9,
    "l": 1290.1,
    "c": 1295.35,
    "v": 350155
  },
  {
    "t": "2024-11-26T14:15:00+05:30",
    "o": 1291.2,
    "h": 1293,
    "l": 1290.55,
    "c": 1290.9,
    "v": 263057
  },
  {
    "t": "2024-11-26T14:00:00+05:30",
    "o": 1291.7,
    "h": 1292.3,
    "l": 1289.25,
    "c": 1291.25,
    "v": 306605
  },
  {
    "t": "2024-11-26T13:45:00+05:30",
    "o": 1289.7,
    "h": 1291.9,
    "l": 1288.7,
    "c": 1291.85,
    "v": 172299
  },
  {
    "t": "2024-11-26T13:30:00+05:30",
    "o": 1289.05,
    "h": 1290,
    "l": 1286.05,
    "c": 1289.95,
    "v": 324664
  },
  {
    "t": "2024-11-26T13:15:00+05:30",
    "o": 1290.05,
    "h": 1291.9,
    "l": 1289,
    "c": 1289.05,
    "v": 155251
  },
  {
    "t": "2024-11-26T13:00:00+05:30",
    "o": 1290.9,
    "h": 1291.95,
    "l": 1289.25,
    "c": 1290.2,
    "v": 194386
  },
  {
    "t": "2024-11-26T12:45:00+05:30",
    "o": 1290,
    "h": 1292,
    "l": 1289.7,
    "c": 1291,
    "v": 156511
  },
  {
    "t": "2024-11-26T12:30:00+05:30",
    "o": 1289.65,
    "h": 1290.85,
    "l": 1288.5,
    "c": 1290.4,
    "v": 187421
  },
  {
    "t": "2024-11-26T12:15:00+05:30",
    "o": 1292.7,
    "h": 1293.35,
    "l": 1288.5,
    "c": 1289.6,
    "v": 264117
  },
  {
    "t": "2024-11-26T12:00:00+05:30",
    "o": 1292.45,
    "h": 1294.3,
    "l": 1291.8,
    "c": 1293,
    "v": 231639
  },
  {
    "t": "2024-11-26T11:45:00+05:30",
    "o": 1293.75,
    "h": 1295.4,
    "l": 1292.05,
    "c": 1292.45,
    "v": 189798
  },
  {
    "t": "2024-11-26T11:30:00+05:30",
    "o": 1292.1,
    "h": 1294.95,
    "l": 1291.5,
    "c": 1293.75,
    "v": 161927
  },
  {
    "t": "2024-11-26T11:15:00+05:30",
    "o": 1293.1,
    "h": 1293.3,
    "l": 1291,
    "c": 1292.1,
    "v": 175017
  },
  {
    "t": "2024-11-26T11:00:00+05:30",
    "o": 1295.9,
    "h": 1296,
    "l": 1292.2,
    "c": 1293.1,
    "v": 290953
  },
  {
    "t": "2024-11-26T10:45:00+05:30",
    "o": 1289.3,
    "h": 1297.65,
    "l": 1289,
    "c": 1296,
    "v": 551417
  },
  {
    "t": "2024-11-26T10:30:00+05:30",
    "o": 1289.4,
    "h": 1290,
    "l": 1287.05,
    "c": 1289.5,
    "v": 201745
  },
  {
    "t": "2024-11-26T10:15:00+05:30",
    "o": 1288.9,
    "h": 1289.95,
    "l": 1285,
    "c": 1289.4,
    "v": 252571
  },
  {
    "t": "2024-11-26T10:00:00+05:30",
    "o": 1285.2,
    "h": 1290.95,
    "l": 1285.05,
    "c": 1288.9,
    "v": 282009
  },
  {
    "t": "2024-11-26T09:45:00+05:30",
    "o": 1285.9,
    "h": 1288.95,
    "l": 1284.2,
    "c": 1285.05,
    "v": 372289
  },
  {
    "t": "2024-11-26T09:30:00+05:30",
    "o": 1290.95,
    "h": 1291.4,
    "l": 1285.35,
    "c": 1285.95,
    "v": 480495
  },
  {
    "t": "2024-11-26T09:15:00+05:30",
    "o": 1294.95,
    "h": 1294.95,
    "l": 1287.2,
    "c": 1290.95,
    "v": 1259578
  },
  {
    "t": "2024-11-25T15:15:00+05:30",
    "o": 1287.25,
    "h": 1292,
    "l": 1285,
    "c": 1290.95,
    "v": 6213482
  },
  {
    "t": "2024-11-25T15:00:00+05:30",
    "o": 1291.6,
    "h": 1293.9,
    "l": 1282.45,
    "c": 1287.25,
    "v": 7730112
  },
  {
    "t": "2024-11-25T14:45:00+05:30",
    "o": 1293.3,
    "h": 1294.3,
    "l": 1290.45,
    "c": 1291.55,
    "v": 396865
  },
  {
    "t": "2024-11-25T14:30:00+05:30",
    "o": 1289.45,
    "h": 1293.55,
    "l": 1287,
    "c": 1293.3,
    "v": 470803
  },
  {
    "t": "2024-11-25T14:15:00+05:30",
    "o": 1289.8,
    "h": 1291.65,
    "l": 1288.65,
    "c": 1289.45,
    "v": 306627
  },
  {
    "t": "2024-11-25T14:00:00+05:30",
    "o": 1289.2,
    "h": 1291.75,
    "l": 1287.95,
    "c": 1289.95,
    "v": 295919
  },
  {
    "t": "2024-11-25T13:45:00+05:30",
    "o": 1285.95,
    "h": 1289.4,
    "l": 1285.15,
    "c": 1289.25,
    "v": 289235
  },
  {
    "t": "2024-11-25T13:30:00+05:30",
    "o": 1292.35,
    "h": 1293.05,
    "l": 1285.85,
    "c": 1286,
    "v": 372866
  },
  {
    "t": "2024-11-25T13:15:00+05:30",
    "o": 1289.1,
    "h": 1293.3,
    "l": 1288.6,
    "c": 1292.4,
    "v": 416404
  },
  {
    "t": "2024-11-25T13:00:00+05:30",
    "o": 1286.25,
    "h": 1290.9,
    "l": 1284.1,
    "c": 1289.1,
    "v": 434099
  },
  {
    "t": "2024-11-25T12:45:00+05:30",
    "o": 1296.8,
    "h": 1297.35,
    "l": 1283.5,
    "c": 1286.25,
    "v": 692872
  },
  {
    "t": "2024-11-25T12:30:00+05:30",
    "o": 1296.15,
    "h": 1297.65,
    "l": 1295,
    "c": 1296.8,
    "v": 328368
  },
  {
    "t": "2024-11-25T12:15:00+05:30",
    "o": 1297.3,
    "h": 1298.4,
    "l": 1293,
    "c": 1296.15,
    "v": 450426
  },
  {
    "t": "2024-11-25T12:00:00+05:30",
    "o": 1293.95,
    "h": 1298.15,
    "l": 1293.6,
    "c": 1297.35,
    "v": 339896
  },
  {
    "t": "2024-11-25T11:45:00+05:30",
    "o": 1297.75,
    "h": 1298,
    "l": 1292.55,
    "c": 1293.95,
    "v": 656077
  },
  {
    "t": "2024-11-25T11:30:00+05:30",
    "o": 1300.5,
    "h": 1300.9,
    "l": 1297.55,
    "c": 1297.8,
    "v": 485690
  },
  {
    "t": "2024-11-25T11:15:00+05:30",
    "o": 1301,
    "h": 1302.2,
    "l": 1298.9,
    "c": 1300.5,
    "v": 475798
  },
  {
    "t": "2024-11-25T11:00:00+05:30",
    "o": 1300.3,
    "h": 1304.45,
    "l": 1300,
    "c": 1300.85,
    "v": 728782
  },
  {
    "t": "2024-11-25T10:45:00+05:30",
    "o": 1298.8,
    "h": 1300.6,
    "l": 1298,
    "c": 1300,
    "v": 570848
  },
  {
    "t": "2024-11-25T10:30:00+05:30",
    "o": 1297.05,
    "h": 1299.35,
    "l": 1296.75,
    "c": 1299.3,
    "v": 492385
  },
  {
    "t": "2024-11-25T10:15:00+05:30",
    "o": 1290.65,
    "h": 1297.1,
    "l": 1290.05,
    "c": 1297.05,
    "v": 491492
  },
  {
    "t": "2024-11-25T10:00:00+05:30",
    "o": 1291.2,
    "h": 1294.9,
    "l": 1290.2,
    "c": 1290.65,
    "v": 457470
  },
  {
    "t": "2024-11-25T09:45:00+05:30",
    "o": 1300.25,
    "h": 1302.85,
    "l": 1290.2,
    "c": 1291.1,
    "v": 1010530
  },
  {
    "t": "2024-11-25T09:30:00+05:30",
    "o": 1299.5,
    "h": 1302,
    "l": 1297.45,
    "c": 1300.3,
    "v": 1041803
  },
  {
    "t": "2024-11-25T09:15:00+05:30",
    "o": 1290,
    "h": 1301.4,
    "l": 1285,
    "c": 1299.45,
    "v": 3426811
  }
]